Workbook

Sheet Deal Overview
B2: Deal Summary | F2: Sensitivity Analysis
B4: Cost Summary | C4: Cost | F4: Scenarios >>> | G4: Disappointed | H4: Conservative | I4: Expected | J4: Aggressive
B5: Purchase Price | C5: ='Sources and Uses'!D5 -> 3200000 | F5: Gross Potential Rent | G5: =H5 -> 1200000 | H5: =I5 -> 1200000 | I5: =Proforma!I5 -> 1200000 | J5: =I5 -> 1200000
B6: ='Sources and Uses'!B9 -> Total Debt | C6: ='Sources and Uses'!D9 -> 2310000 | F6: Vacancy | G6: =H6*1.05 -> -198450 | H6: =I6*1.05 -> -189000 | I6: =Proforma!I6 -> -180000 | J6: =-J5*0.1 -> -120000
B7: Total Fees | C7: ='Sources and Uses'!D23 -> 217750 | F7: Other Income
B8: Total Equity | C8: ='Sources and Uses'!G20 -> 1240000 | F8: Effective Gross Income | G8: =G7+G6+G5 -> 1001550 | H8: =H7+H6+H5 -> 1011000 | I8: =Proforma!I12 -> 1032500 | J8: =J7+J6+J5 -> 1080000
B9: Reserve | C9: ='Sources and Uses'!G19 -> 132250 | F9: Expenses | G9: =H9 -> 666645.79 | H9: =I9 -> 666645.79 | I9: =Proforma!I46 -> 666645.79 | J9: =I9*0.9 -> 599981.21
B10: Total Cost | C10: =C5+C7+C9 -> 3550000 | F10: Management Fees 3rd Party | G10: =H10 -> 10325 | H10: =I10 -> 10325 | I10: =Proforma!I54 -> 10325 | J10: =I10 -> 10325
F11: Vega Asset Management Fees | G11: =H11 -> 10325 | H11: =I11 -> 10325 | I11: =Proforma!I53 -> 10325 | J11: =I11 -> 10325
B12: Total | C12: $ | D12: % | F12: Misc Unexpected Expense Reserve | G12: =H12 -> 51625 | H12: =I12 -> 51625 | I12: =Proforma!I51 -> 51625 | J12: =I12 -> 51625
B13: Equity | C13: =C8 -> 1240000 | D13: =C13/C15 -> 0.34929577 | F13: Net Operating Income | G13: =G8-G9-G10-G11-G12 -> 262629.21 | H13: =H8-H9-H10-H11-H12 -> 272079.21 | I13: =I8-I9-I10-I11-I12 -> 293579.21 | J13: =J8-J9-J10-J11-J12 -> 407743.79
B14: Debt | C14: =C6 -> 2310000 | D14: =C14/C15 -> 0.65070423
B15: Total Required Capital From All Sources | C15: =C14+C13 -> 3550000 | D15: =SUM(D13:D14) -> 1 | F15: Annual Payment | G15: ='Sources and Uses'!$J$9 -> 197691.07 | H15: ='Sources and Uses'!$J$9 -> 197691.07 | I15: ='Sources and Uses'!$J$9 -> 197691.07 | J15: ='Sources and Uses'!$J$9 -> 197691.07
F16: Cash Flow | G16: =G13-G15 -> 64938.139 | H16: =H13-H15 -> 74388.139 | I16: =I13-I15 -> 95888.139 | J16: =J13-J15 -> 210052.72
B17: Total | D17: % | F17: Investor Pref | G17: =H17 -> 99200 | H17: =I17 -> 99200 | I17: =D18*'Sources and Uses'!D13 -> 99200 | J17: =I17 -> 99200
B18: Investor Pref | D18: 0.08 | F18: Remaining | G18: =if((G16-G17)>0,G16-G17,"") | H18: =if((H16-H17)>0,H16-H17,"") | I18: =if((I16-I17)>0,I16-I17,"") | J18: =if((J16-J17)>0,J16-J17,"") -> 110852.72
B19: Sponsor Promote | C19: =C11 | D19: 0.5 | F19: Investor Split | G19: =G18/2 -> 0 | H19: =H18/2 -> 0 | I19: =I18/2 -> 0 | J19: =J18/2 -> 55426.359
F20: Sponsor Split | G20: =G19 -> 0 | H20: =H19 -> 0 | I20: =I19 -> 0 | J20: =J19 -> 55426.359
F21: Total Investor Cash Flow Upon Stabilization | G21: =if((G16-G17)>0,G19+G17,G16) -> 64938.139 | H21: =if((H16-H17)>0,H19+H17,H16) -> 74388.139 | I21: =if((I16-I17)>0,I19+I17,I16) -> 95888.139 | J21: =if((J16-J17)>0,J19+J17,J16) -> 154626.36
F22: 1st Year Cash on Cash | G22: =G21/'Sources and Uses'!$D$13 -> 0.052369467 | H22: =H21/'Sources and Uses'!$D$13 -> 0.059990435 | I22: =I21/'Sources and Uses'!$D$13 -> 0.077329144 | J22: =J21/'Sources and Uses'!$D$13 -> 0.12469868
F23: 1st Year Principal Reduction | G23: =H23 -> 0.028063722 | H23: =I23 -> 0.028063722 | I23: =-'Sources and Uses'!M8/'Sources and Uses'!D13 -> 0.028063722 | J23: =I23 -> 0.028063722
F24: Total 1st Year benefit | G24: =G23+G22 -> 0.08043319 | H24: =H23+H22 -> 0.088054157 | I24: =I23+I22 -> 0.10539287 | J24: =J23+J22 -> 0.1527624

Sheet Sam Copy of Deal Overview
B2: Deal Summary | F2: Sensitivity Analysis
B4: Cost Summary | C4: Cost | F4: Scenarios >>> | G4: Disappointed | H4: Conservative | I4: Expected | J4: Aggressive
B5: Purchase Price | C5: ='Sources and Uses'!D5 -> 3200000 | F5: Gross Potential Rent | G5: =H5 -> 1200000 | H5: =I5 -> 1200000 | I5: =Proforma!I5 -> 1200000 | J5: =I5 -> 1200000
B6: ='Sources and Uses'!B9 -> Total Debt | C6: ='Sources and Uses'!D9 -> 2310000 | F6: Vacancy | G6: =H6*1.05 -> -198450 | H6: =I6*1.05 -> -189000 | I6: =Proforma!I6 -> -180000 | J6: =-J5*0.1 -> -120000
B7: Total Fees | C7: ='Sources and Uses'!D23 -> 217750 | F7: Other Income
B8: Total Equity | C8: ='Sources and Uses'!G20 -> 1240000 | F8: Effective Gross Income | G8: =G7+G6+G5 -> 1001550 | H8: =H7+H6+H5 -> 1011000 | I8: =Proforma!I12 -> 1032500 | J8: =J7+J6+J5 -> 1080000
B9: Reserve | C9: ='Sources and Uses'!G19 -> 132250 | F9: Expenses | G9: =H9 -> 666645.79 | H9: =I9 -> 666645.79 | I9: =Proforma!I46 -> 666645.79 | J9: =I9*0.9 -> 599981.21
B10: Total Cost | C10: =C5+C7+C9 -> 3550000 | F10: Management Fees 3rd Party | G10: =H10 -> 10325 | H10: =I10 -> 10325 | I10: =Proforma!I54 -> 10325 | J10: =I10 -> 10325
F11: Vega Asset Management Fees | G11: =H11 -> 10325 | H11: =I11 -> 10325 | I11: =Proforma!I53 -> 10325 | J11: =I11 -> 10325
B12: Total | C12: $ | D12: % | F12: Misc Unexpected Expense Reserve | G12: =H12 -> 51625 | H12: =I12 -> 51625 | I12: =Proforma!I51 -> 51625 | J12: =I12 -> 51625
B13: Equity | C13: =C8 -> 1240000 | D13: =C13/C15 -> 0.34929577 | F13: Net Operating Income | G13: =G8-G9-G10-G11-G12 -> 262629.21 | H13: =H8-H9-H10-H11-H12 -> 272079.21 | I13: =I8-I9-I10-I11-I12 -> 293579.21 | J13: =J8-J9-J10-J11-J12 -> 407743.79
B14: Debt | C14: =C6 -> 2310000 | D14: =C14/C15 -> 0.65070423
B15: Total Required Capital From All Sources | C15: =C14+C13 -> 3550000 | D15: =SUM(D13:D14) -> 1 | F15: Annual Payment | G15: ='Sources and Uses'!$J$9 -> 197691.07 | H15: ='Sources and Uses'!$J$9 -> 197691.07 | I15: ='Sources and Uses'!$J$9 -> 197691.07 | J15: ='Sources and Uses'!$J$9 -> 197691.07
F16: Cash Flow | G16: =G13-G15 -> 64938.139 | H16: =H13-H15 -> 74388.139 | I16: =I13-I15 -> 95888.139 | J16: =J13-J15 -> 210052.72
B17: Total | D17: % | F17: Investor Pref | G17: =H17 -> 99200 | H17: =I17 -> 99200 | I17: =D18*'Sources and Uses'!D13 -> 99200 | J17: =I17 -> 99200
B18: Investor Pref | D18: 0.08 | F18: Remaining | G18: =if((G16-G17)>0,G16-G17,"") | H18: =if((H16-H17)>0,H16-H17,"") | I18: =if((I16-I17)>0,I16-I17,"") | J18: =if((J16-J17)>0,J16-J17,"") -> 110852.72
B19: Sponsor Promote | C19: =C11 | D19: 0.5 | F19: Investor Split | G19: =G18/2 -> 0 | H19: =H18/2 -> 0 | I19: =I18/2 -> 0 | J19: =J18/2 -> 55426.359
F20: Sponsor Split | G20: =G19 -> 0 | H20: =H19 -> 0 | I20: =I19 -> 0 | J20: =J19 -> 55426.359
F21: Total Investor Cash Flow Upon Stabilization | G21: =if((G16-G17)>0,G19+G17,G16) -> 64938.139 | H21: =if((H16-H17)>0,H19+H17,H16) -> 74388.139 | I21: =if((I16-I17)>0,I19+I17,I16) -> 95888.139 | J21: =if((J16-J17)>0,J19+J17,J16) -> 154626.36
F22: 1st Year Cash on Cash | G22: =G21/'Sources and Uses'!$D$13 -> 0.052369467 | H22: =H21/'Sources and Uses'!$D$13 -> 0.059990435 | I22: =I21/'Sources and Uses'!$D$13 -> 0.077329144 | J22: =J21/'Sources and Uses'!$D$13 -> 0.12469868
F23: 1st Year Principal Reduction | G23: =H23 -> 0.028063722 | H23: =I23 -> 0.028063722 | I23: =-'Sources and Uses'!M8/'Sources and Uses'!D13 -> 0.028063722 | J23: =I23 -> 0.028063722
F24: Total 1st Year benefit | G24: =G23+G22 -> 0.08043319 | H24: =H23+H22 -> 0.088054157 | I24: =I23+I22 -> 0.10539287 | J24: =J23+J22 -> 0.1527624
F26: 2nd Year Cash on Cash | I26: =Proforma!J64/'Sources and Uses'!$D$13 -> 0.083482567
F27: 2nd Year Principal Reduction | I27: =-'Sources and Uses'!N8/'Sources and Uses'!$D$13 -> 0.030122383
F28: Total 2ndYear benefit | I28: =I27+I26 -> 0.11360495
F30: 3rd Year Cash on Cash | I30: =Proforma!K64/'Sources and Uses'!$D$13 -> 0.088579456
F31: 3rd Year Principal Reduction | I31: =-'Sources and Uses'!O8/'Sources and Uses'!$D$13 -> 0.03233206
F32: Total 3rdYear benefit | I32: =I31+I30 -> 0.12091152
F34: 4th Year Cash on Cash | I34: =Proforma!L64/'Sources and Uses'!$D$13 -> 0.093990477
F35: 4thYear Principal Reduction | I35: =-'Sources and Uses'!P8/'Sources and Uses'!$D$13 -> 0.034703831
F36: Total 4th Year benefit | I36: =I35+I34 -> 0.12869431
F38: 5th Year Cash on Cash | I38: =Proforma!M64/'Sources and Uses'!$D$13 -> 0.099757301
F39: 5th Year Principal Reduction | I39: =-'Sources and Uses'!Q8/'Sources and Uses'!$D$13 -> 0.037249587
F40: Total 5th Year benefit | I40: =I39+I38 -> 0.13700689
K41: Annualized Return
F42: Total Cash on Cash | I42: =SUM(I21,Proforma!J64,Proforma!K64,Proforma!L64,Proforma!M64)/'Sources and Uses'!D13 -> 0.44313895 | K42: =I42/5 -> 0.088627789
F43: Total Principal Reduction | I43: =-SUM('Sources and Uses'!M8,'Sources and Uses'!N8,'Sources and Uses'!O8,'Sources and Uses'!P8,'Sources and Uses'!Q8)/'Sources and Uses'!D13 -> 0.16247158 | K43: =I43/5 -> 0.032494317
F44: Total benefit | I44: =I43+I42 -> 0.60561053 | K44: =I44/5 -> 0.12112211
F47: Target Exit Price (8% Cap Rate) | G47: =Proforma!M47/0.08 -> 5261741
F48: Sale Cost at Year 3 | G48: =G47*0.06 -> 315704.46
F49: Loan Balance at Year 3 | G49: ='Sources and Uses'!Q9 -> 2108535.2
F50: Net Proceeds at Sale End of Year 3 | G50: =G47-G48-G49 -> 2837501.3
F51: Profit | G51: =G50-C8 -> 1597501.3
F52: Sponsor Fees | G52: =G51/2 -> 798750.63
F53: Total Investor Benefit | G53: =G52+-SUM('Sources and Uses'!M8:Q8)+Proforma!I64+Proforma!J64+Proforma!K64+Proforma!L64+Proforma!M64 -> 1549707.7
F54: Total Investor Return | G54: =(G53)/C13 -> 1.2497643
F55: Annualized Return | G55: =G54/5 -> 0.24995285

Sheet Sources and Uses
B2: Sources and Uses of Funds
B4: Acquisition Assumptions | F4: Lender | G4: Amount | H4: Interest Rate | I4: Term | J4: Monthly Payment | L4: Principal Reduction | M4: Year 1 | N4: Year 2 | O4: Year 3 | P4: Year 4 | Q4: Year 5
B5: Total Project Cost | D5: 3200000 | F5: 1st Position | G5: =D6 -> 2310000 | H5: 0.071 | I5: 25 | J5: =PMT(H5/12,I5*12,-G5,0,0) -> 16474.256 | M5: =iferror(CUMPRINC(H5/12,I5*12,G5,1,12,0),"") -> -34799.016 | N5: =iferror(CUMPRINC(H5/12,I5*12,G5,13,24,0),"") -> -37351.755 | O5: =iferror(CUMPRINC(H5/12,I5*12,G5,25,36,0),"") -> -40091.754 | P5: =iferror(CUMPRINC(H5/12,I5*12,G5,37,48,0),"") -> -43032.75 | Q5: =iferror(CUMPRINC(H5/12,I5*12,G5,49,60,0),"") -> -46189.488
B6: 1st Position Loan (Bank) | D6: 2310000 | F6: 2nd Position | G6: =D7 -> 0 | H6: 0.0675 | I6: 25 | J6: =PMT(H6/12,I6*12,-G6,0,1) -> 0 | M6: =iferror(CUMPRINC(H6/12,I6*12,G6,1,12,0),"") | N6: =iferror(CUMPRINC(H6/12,I6*12,G6,13,24,0),"") | O6: =iferror(CUMPRINC(H6/12,I6*12,G6,25,36,0),"") | P6: =iferror(CUMPRINC(H6/12,I6*12,G6,37,48,0),"") | Q6: =iferror(CUMPRINC(H6/12,I6*12,G6,49,60,0),"")
B7: 2nd Position Loan (SBA) | C7: 0 | D7: =C7*D5 -> 0 | F7: Seller | G7: =D8 -> 0 | H7: 0.05 | I7: 25 | J7: =PMT(H7/12,I7*12,-G7,0,1) -> 0 | M7: =iferror(CUMPRINC(H7/12,I7*12,G7,1,12,0),"") | N7: =iferror(CUMPRINC(H7/12,I7*12,G7,13,24,0),"") | O7: =iferror(CUMPRINC(H7/12,I7*12,G7,25,36,0),"") | P7: =iferror(CUMPRINC(H7/12,I7*12,G7,37,48,0),"") | Q7: =iferror(CUMPRINC(H7/12,I7*12,G7,49,60,0),"")
B8: 3rd Position Seller Finance | C8: 0 | D8: =C8*D5 -> 0 | F8: Total | G8: =G6+G5+G7 -> 2310000 | I8: Monthly Debt Service | J8: =J6+J5+J7 -> 16474.256 | L8: Total Principal Reduction | M8: =sum(M5:M7) -> -34799.016 | N8: =sum(N5:N7) -> -37351.755 | O8: =sum(O5:O7) -> -40091.754 | P8: =sum(P5:P7) -> -43032.75 | Q8: =sum(Q5:Q7) -> -46189.488
B9: Total Debt | D9: =D8+D7+D6 -> 2310000 | I9: Annual Debt Service | J9: =J8*12 -> 197691.07 | L9: Loan Balance | M9: =G8+M8 -> 2275201 | N9: =N8+M9 -> 2237849.2 | O9: =O8+N9 -> 2197757.5 | P9: =P8+O9 -> 2154724.7 | Q9: =Q8+P9 -> 2108535.2
B10: Down Payment | D10: =D5-D6-D7-D8 -> 890000
B11: Reserve | C11: =D11/D5 -> 0.041328125 | D11: =1240000-1107750 -> 132250 | J11: =J5-16443.62 -> 30.635908
B12: Fees | D12: =D23 -> 217750
B13: Total Equity | D13: =D12+D11+D10 -> 1240000 | J13: 23588.76 | M13: =M8/$G$20 -> -0.028063722 | N13: =N8/$G$20 -> -0.030122383 | O13: =O8/$G$20 -> -0.03233206 | P13: =P8/$G$20 -> -0.034703831 | Q13: =Q8/$G$20 -> -0.037249587
B14: Total Sources and Uses | D14: =D13+D9 -> 3550000 | J14: =J13*12 -> 283065.12
B16: Fees | F16: Sources and Uses of Funds
B17: Bank Fees | C17: 0.015 | D17: =C17*D9 -> 34650 | F17: Bank Required Down Payment | G17: =D10 -> 890000
B18: Vega Capital Markets Fee | C18: 0.01 | D18: =C18*D9 -> 23100 | F18: Fees | G18: =D23 -> 217750
B19: Acquisition Fee | C19: 0.03 | D19: =C19*D5 -> 96000 | F19: Reserve | G19: =D11 -> 132250
B20: Due Diligence Costs | C20: 0.01 | D20: =C20*D5 -> 32000 | F20: Total | G20: =SUM(G17:G19) -> 1240000
B21: Closing Costs | C21: 0.01 | D21: =C21*D5 -> 32000
B23: Total | D23: =SUM(D17:D22) -> 217750
H24: =2407500/3200000 -> 0.75234375
H26: =1250000-806000 -> 444000
G27: =G20*0.6563 -> 813812
F34: Heritage | G34: 186078
F35: PHillip | G35: 110089
F36: Summit | G36: 65000
F37: Utah Bank | G37: 65000
F38: Fund II | G38: 598172.68
G39: =sum(G34:G38) -> 1024339.7
G40: 20000
G41: =G40+G39 -> 1044339.7
G42: 190953.66
G43: =G42+G41 -> 1235293.3
G44: =G20-G43 -> 4706.66
G49: TIC Agreement | H49: Closing Docs | J49: Fund II ***8204
B50: Journal Entry 1 - Acquisition fees | F50: Ownership | G50: Ownership | H50: Equity | I50: Current Funds | J50: Transfer
B51: Account | C51: Debits | D51: Credits | F51: Fund II - Vega Cedar City AL LLC | G51: 0.6563 | H51: =G51*$G$20 -> 813812 | I51: 598172.68 | J51: =H51-I51 -> 215639.32
B52: Acqusiition Fees | C52: =D19 -> 96000 | F52: Phillip Chipping | G52: 0.0888 | H52: =G52*$G$20 -> 110112 | I52: =D72 -> 190953.66
B53: Capital From Vega Assisted Living Fund II, LP | D53: 96000 | F53: Heritage Storage LLC | G53: 0.1501 | H53: =G53*$G$20 -> 186124 | I53: =I52+I51 -> 789126.34 | J53: =H51-I53 -> 24685.66 | L53: <---- This includes the capital for the excess land
B54: Total | C54: =C53+C52 -> 96000 | D54: =D53+D52 -> 96000 | F54: Summit Home Solutions LC | G54: 0.0524 | H54: =G54*$G$20 -> 64976
F55: Utah Bankruptcy Inc. | G55: 0.0524 | H55: =G55*$G$20 -> 64976
B56: Journal Entry 2 - Building/Mortgages | F56: Total | G56: =sum(G51:G55) -> 1 | H56: =sum(H51:H55) -> 1240000
B57: Account | C57: Debits | D57: Credits
B58: Buildings | C58: =3200000-C59 -> 2878663 | F58: To Townhomes
B59: Land | C59: =321337 -> 321337
B60: Mortgages | D60: 2310000
B61: Capital from Summit Home Solutions | D61: 65000 | F61: =104000-D61 -> 39000
B62: Capital from Utah Bankruptcy Inc. | D62: 65000 | F62: =104000-D62 -> 39000
B63: Capital from Phillip Chipping | D63: 110089
B64: Capital from Heritage Storage | D64: 186078 | F64: =40000+332156-D64 -> 186078
B65: Capital from Vega Assisted Living Fund II | D65: 497127
B66: Acqusiition Fee | C66: 96000
B67: Inspections | C67: 999
B68: Legal | C68: 1200
B69: Insurance | C69: 2846.68
B70: Capital from Vega Assisted Living Fund II | D70: 101045.68
B71: Excess Land | C71: 190953.66
B72: Excess Land Capital from Vega Assisted Living Fund II | D72: 190953.66
B73: Closing Costs | C73: 33294
B74: Total | C74: =sum(C58:C73) -> 3525293.3 | D74: =sum(D58:D73) -> 3525293.3
B76: Fund II Journal Entry - Credit from Vega Property Holdings LLC
B77: Account | C77: Debits | D77: Credits | F77: Balance Sheet | G77: 46048
B78: LP Capital Contributions | C78: =D37 | D78: 96000 | F78: Funds in Property Balance Sheet from Fund II | G78: 598172.68
B79: Vega Sandy City AL LLC | C79: 96000 | F79: Funds in Fund Balance Sheet for Property | G79: 598172.68
B80: Total | C80: =C79+C78 -> 96000 | D80: =D79+D78 -> 96000
B82: Loan Consulting Fee Paid to Vega Capital Markets LLC
B83: Paid - transferred on | C83: 45683 | D83: 23100
B85: There is $20,000 in Vega Capital Stack
B86: Opening Balance EQuity

Sheet Bank Proforma
C2: 3 Year Historicals (Actuals)
C4: Year | D4: 2022 | E4: 2023 | F4: 2024 | G4: 2025 YTD (march) | H4: 2025 Annualized | I4: Proforma Year 1 | J4: Proforma Year 2 | K4: Proforma Year 3 | L4: Proforma Year 4 | M4: Proforma Year 5
C5: Potential Income | I5: =5000*20*12 -> 1200000 | J5: =I5*1.03 -> 1236000 | K5: =J5*1.03 -> 1273080 | L5: =K5*1.03 -> 1311272.4 | M5: =L5*1.03 -> 1350610.6 | O5: =I5/12 -> 100000
C6: Vacancy | I6: =-I5*0.08 -> -96000 | J6: =-J5*0.08 -> -98880 | K6: =-K5*0.08 -> -101846.4 | L6: =-L5*0.08 -> -104901.79 | M6: =-M5*0.08 -> -108048.85 | O6: =I6/12 -> -8000
C7: Income | O7: =I7/12 -> 0
C8: Day Care | I8: 5000 | J8: =I8*1.2 -> 6000 | K8: =J8*1.2 -> 7200 | L8: =K8*1.2 -> 8640 | M8: =L8*1.2 -> 10368 | O8: =I8/12 -> 416.66667
C9: Other Income | I9: 2500 | J9: =I9 -> 2500 | K9: =J9 -> 2500 | L9: =K9 -> 2500 | M9: =L9 -> 2500 | O9: =I9/12 -> 208.33333
C10: Rental Income | D10: 762385.9 | E10: 898360.99 | F10: 982748.03 | G10: 229323.19 | H10: =G10*4 -> 917292.76 | I10: =I5+I6 -> 1104000 | J10: =J5+J6 -> 1137120 | K10: =K5+K6 -> 1171233.6 | L10: =L5+L6 -> 1206370.6 | M10: =M5+M6 -> 1242561.7 | O10: =I10/12 -> 92000
C11: Move In Fees | I11: 5000 | J11: =I11*1.2 -> 6000 | K11: =J11*1.2 -> 7200 | L11: =K11*1.2 -> 8640 | M11: =L11*1.2 -> 10368 | N11: =N12-I12 -> 58300 | O11: =I11/12 -> 416.66667
C12: Total Income | D12: =SUM(D8:D11) -> 762385.9 | E12: =SUM(E8:E11) -> 898360.99 | F12: =SUM(F8:F11) -> 982748.03 | G12: =SUM(G8:G11) -> 229323.19 | H12: =SUM(H8:H11) -> 917292.76 | I12: =SUM(I8:I11) -> 1116500 | J12: =SUM(J8:J11) -> 1151620 | K12: =SUM(K8:K11) -> 1188133.6 | ... M12: =SUM(M8:M11) -> 1265797.7 | N12: =N13*12 -> 1174800 | O12: =I12/12 -> 93041.667
I13: =I12/12 -> 93041.667 | N13: 97900 | O13: =I13/12 -> 7753.4722
C14: Expenses | O14: =I14/12 -> 0
C15: Accounting | D15: $ - | E15: 1200 | F15: 11028.5 | G15: 1755 | H15: =G15*4 -> 7020 | I15: 8000 | J15: =I15*1.03 -> 8240 | K15: =J15*1.03 -> 8487.2 | L15: =K15*1.03 -> 8741.816 | M15: =L15*1.03 -> 9004.0705 | O15: =I15/12 -> 666.66667
C16: Advertising/Promotional | D16: 5965.18 | E16: 1525.14 | F16: 6522.48 | G16: 606.38 | H16: =G16*4 -> 2425.52 | I16: 6500 | J16: =I16*1.03 -> 6695 | K16: =J16*1.03 -> 6895.85 | L16: =K16*1.03 -> 7102.7255 | M16: =L16*1.03 -> 7315.8073 | O16: =I16/12 -> 541.66667
C17: Bank Charges | D17: 2 | E17: 1455.2 | F17: 1158.92 | G17: 75 | H17: =G17*4 -> 300 | I17: 1200 | J17: =I17*1.03 -> 1236 | K17: =J17*1.03 -> 1273.08 | L17: =K17*1.03 -> 1311.2724 | M17: =L17*1.03 -> 1350.6106 | O17: =I17/12 -> 100
C18: Business licenses/Permits | D18: 2317 | E18: 2689 | F18: 829 | H18: =G18*4 -> 0 | I18: 2500 | J18: =I18*1.03 -> 2575 | K18: =J18*1.03 -> 2652.25 | L18: =K18*1.03 -> 2731.8175 | M18: =L18*1.03 -> 2813.772 | O18: =I18/12 -> 208.33333
C19: Nursing | D19: 3067.5 | E19: 3745 | F19: 4617.5 | G19: 957.5 | H19: =G19*4 -> 3830 | I19: 4500 | J19: =I19*1.03 -> 4635 | K19: =J19*1.03 -> 4774.05 | L19: =K19*1.03 -> 4917.2715 | M19: =L19*1.03 -> 5064.7896 | O19: =I19/12 -> 375
C20: Dietician | H20: =G20*4 -> 0 | J20: =I20*1.03 -> 0 | K20: =J20*1.03 -> 0 | L20: =K20*1.03 -> 0 | M20: =L20*1.03 -> 0 | O20: =I20/12 -> 0
C21: Dues & Subscriptions | D21: 1918.81 | E21: 1699.73 | F21: 5171.09 | G21: 1305.48 | H21: =G21*4 -> 5221.92 | I21: 2500 | J21: =I21*1.03 -> 2575 | K21: =J21*1.03 -> 2652.25 | L21: =K21*1.03 -> 2731.8175 | M21: =L21*1.03 -> 2813.772 | O21: =I21/12 -> 208.33333
C22: Administrator Expense | D22: 65000 | E22: 65000 | F22: 65000 | G22: =65000/4 -> 16250 | H22: =G22*4 -> 65000 | I22: 65000 | J22: =I22*1.03 -> 66950 | K22: =J22*1.03 -> 68958.5 | L22: =K22*1.03 -> 71027.255 | M22: =L22*1.03 -> 73158.073 | O22: =I22/12 -> 5416.6667
C23: Employee Expenses | D23: =372150.03-D22+2021.49+179 -> 309350.52 | E23: =516817.64-E22+752.07+1162.79 -> 453732.5 | F23: =543985.31-F22+1707.34+100 -> 480792.65 | G23: =133613.48-G22+98.35 -> 117461.83 | H23: =G23*4 -> 469847.32 | I23: 450000 | J23: =I23*1.03 -> 463500 | K23: =J23*1.03 -> 477405 | L23: =K23*1.03 -> 491727.15 | M23: =L23*1.03 -> 506478.96 | O23: =I23/12 -> 37500
C24: Franchise Fees | H24: =G24*4 -> 0 | I24: 0 | J24: =I24*1.03 -> 0 | K24: =J24*1.03 -> 0 | L24: =K24*1.03 -> 0 | M24: =L24*1.03 -> 0 | O24: =I24/12 -> 0
C25: Cleaning | H25: =G25*4 -> 0 | I25: 0 | J25: =I25*1.03 -> 0 | K25: =J25*1.03 -> 0 | L25: =K25*1.03 -> 0 | M25: =L25*1.03 -> 0 | O25: =I25/12 -> 0
C26: Household Supplies | D26: =8223.22+10820.73 -> 19043.95 | E26: =4866.29-13.35 -> 4852.94 | F26: =3711.27+1099.43 -> 4810.7 | G26: =699.96+277.55 -> 977.51 | H26: =G26*4 -> 3910.04 | I26: 5000 | J26: =I26*1.03 -> 5150 | K26: =J26*1.03 -> 5304.5 | L26: =K26*1.03 -> 5463.635 | M26: =L26*1.03 -> 5627.5441 | O26: =I26/12 -> 416.66667
C27: Management Fees | H27: =G27*4 -> 0 | I27: 0 | J27: =I27*1.03 -> 0 | K27: =J27*1.03 -> 0 | L27: =K27*1.03 -> 0 | M27: =L27*1.03 -> 0 | O27: =I27/12 -> 0
C28: General business expenses | H28: =G28*4 -> 0 | I28: 0 | J28: =I28*1.03 -> 0 | K28: =J28*1.03 -> 0 | L28: =K28*1.03 -> 0 | M28: =L28*1.03 -> 0 | O28: =I28/12 -> 0
C29: Insurance | D29: 1389.84 | E29: $ - | F29: 21949.61 | G29: 327 | H29: =G29*4 -> 1308 | I29: 21949.61 | J29: =I29*1.03 -> 22608.098 | K29: =J29*1.03 -> 23286.341 | L29: =K29*1.03 -> 23984.931 | M29: =L29*1.03 -> 24704.479 | O29: =I29/12 -> 1829.1342
C30: Liability insurance | H30: =G30*4 -> 0 | J30: =I30*1.03 -> 0 | K30: =J30*1.03 -> 0 | L30: =K30*1.03 -> 0 | M30: =L30*1.03 -> 0 | O30: =I30/12 -> 0
C31: Property insurance | H31: =G31*4 -> 0 | J31: =I31*1.03 -> 0 | K31: =J31*1.03 -> 0 | L31: =K31*1.03 -> 0 | M31: =L31*1.03 -> 0 | O31: =I31/12 -> 0
C32: Lease Payments - Equipment | D32: 200 | F32: 783.82 | G32: 98.2 | H32: =G32*4 -> 392.8 | I32: 785 | J32: =I32*1.03 -> 808.55 | K32: =J32*1.03 -> 832.8065 | L32: =K32*1.03 -> 857.7907 | M32: =L32*1.03 -> 883.52442 | O32: =I32/12 -> 65.416667
C33: Medical Supplies | D33: 6602.89 | E33: 3349.16 | F33: 4064.08 | G33: 759.82 | H33: =G33*4 -> 3039.28 | I33: 4500 | J33: =I33*1.03 -> 4635 | K33: =J33*1.03 -> 4774.05 | L33: =K33*1.03 -> 4917.2715 | M33: =L33*1.03 -> 5064.7896 | O33: =I33/12 -> 375
C34: Office expenses | D34: =43.3+950.68 -> 993.98 | E34: =161.88+27.49+659.21 -> 848.58 | F34: =744.4+99.66+25.86 -> 869.92 | G34: =1060.03+12.25+97.12 -> 1169.4 | H34: =G34*4 -> 4677.6 | I34: 1000 | J34: =I34*1.03 -> 1030 | K34: =J34*1.03 -> 1060.9 | L34: =K34*1.03 -> 1092.727 | M34: =L34*1.03 -> 1125.5088 | O34: =I34/12 -> 83.333333
C35: Operations Contract Service | D35: 1206.29 | E35: 1308 | F35: 1309.9 | G35: 426.2 | H35: =G35*4 -> 1704.8 | I35: 1500 | J35: =I35*1.03 -> 1545 | K35: =J35*1.03 -> 1591.35 | L35: =K35*1.03 -> 1639.0905 | M35: =L35*1.03 -> 1688.2632 | O35: =I35/12 -> 125
C36: Placement Fees | H36: =G36*4 -> 0 | J36: =I36*1.03 -> 0 | K36: =J36*1.03 -> 0 | L36: =K36*1.03 -> 0 | M36: =L36*1.03 -> 0 | O36: =I36/12 -> 0
C37: Raw Food | D37: 35749.36 | E37: 40486.08 | F37: 36303.32 | G37: 8753.37 | H37: =G37*4 -> 35013.48 | I37: 40000 | J37: =I37*1.03 -> 41200 | K37: =J37*1.03 -> 42436 | L37: =K37*1.03 -> 43709.08 | M37: =L37*1.03 -> 45020.352 | O37: =I37/12 -> 3333.3333
C38: Repairs & maintenance | D38: 19962.91 | E38: =1110.41+8499.21 -> 9609.62 | F38: =1029.82+12540.51 -> 13570.33 | G38: =1196.79+1240.18 -> 2436.97 | H38: =G38*4 -> 9747.88 | I38: 15000 | J38: =I38*1.03 -> 15450 | K38: =J38*1.03 -> 15913.5 | L38: =K38*1.03 -> 16390.905 | M38: =L38*1.03 -> 16882.632 | O38: =I38/12 -> 1250
C39: Resident Activities | D39: 520.38 | E39: 903.39 | F39: 945.64 | G39: 169 | H39: =G39*4 -> 676 | I39: 2500 | J39: =I39*1.03 -> 2575 | K39: =J39*1.03 -> 2652.25 | L39: =K39*1.03 -> 2731.8175 | M39: =L39*1.03 -> 2813.772 | O39: =I39/12 -> 208.33333
C40: Taxes paid | D40: 830.29 | E40: 25122.8 | F40: 9.7 | H40: =G40*4 -> 0 | I40: 9711.18 | J40: =I40*1.03 -> 10002.515 | K40: =J40*1.03 -> 10302.591 | L40: =K40*1.03 -> 10611.669 | M40: =L40*1.03 -> 10930.019 | O40: =I40/12 -> 809.265
C41: Property taxes | H41: =G41*4 -> 0 | J41: =I41*1.03 -> 0 | K41: =J41*1.03 -> 0 | L41: =K41*1.03 -> 0 | M41: =L41*1.03 -> 0 | O41: =I41/12 -> 0
C42: Personal Property Taxes | H42: =G42*4 -> 0 | O42: =I42/12 -> 0
C43: Travel/Vehicle | H43: =G43*4 -> 0 | J43: =I43*1.03 -> 0 | K43: =J43*1.03 -> 0 | L43: =K43*1.03 -> 0 | M43: =L43*1.03 -> 0 | O43: =I43/12 -> 0
C44: Utilities | D44: 20822.61 | E44: 22200 | F44: 22898.16 | G44: 7152.11 | H44: =G44*4 -> 28608.44 | I44: 23000 | J44: =I44*1.03 -> 23690 | K44: =J44*1.03 -> 24400.7 | L44: =K44*1.03 -> 25132.721 | M44: =L44*1.03 -> 25886.703 | O44: =I44/12 -> 1916.6667
C45: Misc Expense | D45: 639 | E45: 981.62 | F45: 349.5 | H45: =G45*4 -> 0 | I45: 1500 | J45: =I45*1.03 -> 1545 | K45: =J45*1.03 -> 1591.35 | L45: =K45*1.03 -> 1639.0905 | M45: =L45*1.03 -> 1688.2632 | O45: =I45/12 -> 125
C46: Total Expenses | D46: =SUM(D15:D45) -> 495582.51 | E46: =SUM(E15:E45) -> 640708.76 | F46: =SUM(F15:F45) -> 682984.82 | G46: =SUM(G15:G45) -> 160680.77 | H46: =SUM(H15:H45) -> 642723.08 | I46: =SUM(I15:I45) -> 666645.79 | J46: =SUM(J15:J45) -> 686645.16 | K46: =SUM(K15:K45) -> 707244.52 | ... M46: =SUM(M15:M45) -> 750315.71 | N46: =I46 -> 666645.79 | O46: =I46/12 -> 55553.816
C47: Net Operating Income | D47: =D12-D46 -> 266803.39 | E47: =E12-E46 -> 257652.23 | F47: =F12-F46 -> 299763.21 | G47: =G12-G46 -> 68642.42 | H47: =H12-H46 -> 274569.68 | I47: =I12-I46 -> 449854.21 | J47: =J12-J46 -> 464974.84 | K47: =K12-K46 -> 480889.08 | ... N47: =N12-N46 -> 508154.21 | O47: =I47/12 -> 37487.851
N49: =N47/'Sources and Uses'!$D$5 -> 0.15879819
N50: =I46/(N13*12) -> 0.56745471
N51: 20000
N52: =I52
N53: =N12*0.01 -> 11748
N54: =N12*$H$54 -> 0
N55: =N47-N51-N52-N53-N54 -> 476406.21
N56: =N55/'Sources and Uses'!$G$20 -> 0.38419856
N57: ='Sources and Uses'!Q8 -> -46189.488
N58: ='Sources and Uses'!R9
N59: =N47/0.08 -> 6351927.6
N60: =N59*0.06 -> 381115.66
N61: =N59-N60-N58 -> 5970812
N62: ='Sources and Uses'!$D$13*$D$62 -> 0
N63: =if((N55-N62)>0,(N55-N62)/2,0) -> 238203.11
N64: =N55-N63 -> 238203.11
N65: =N64/'Sources and Uses'!$D$13 -> 0.19209928

Sheet 3 Year Proforma
C2: Proforma | J2: Actuals
D4: Year 1 | E4: Year 2 | F4: Year 3 | G4: Year 4 | H4: Year 5 | K4: =Proforma!D4 -> 2022 | L4: =Proforma!E4 -> 2023 | M4: =Proforma!F4 -> 2024 | N4: =Proforma!G4 -> 2025 YTD (march) | O4: =Proforma!H4 -> 2025 Annualized
C5: Gross Potential Rent | D5: =166554.6*12 -> 1998655.2 | E5: =D5*1.03 -> 2058614.9 | F5: =E5*1.03 -> 2120373.3
C6: Vacancy @ 5% | D6: =D5*-0.086 -> -171884.35 | E6: =E5*-0.086 -> -177040.88 | F6: =F5*-0.086 -> -182352.1
C7: Other Income | D7: =2842.28*12 -> 34107.36 | E7: =2842.28*12 -> 34107.36 | F7: =2842.28*12 -> 34107.36
C8: Effective Gross Income | D8: =Proforma!I12 -> 1032500 | E8: =Proforma!J12 -> 1065100 | F8: =Proforma!K12 -> 1099018 | G8: =Proforma!L12 -> 1134361.5 | H8: =Proforma!M12 -> 1171255 | J8: =C8 -> Effective Gross Income | K8: =Proforma!D12 -> 762385.9 | L8: =Proforma!E12 -> 898360.99 | M8: =Proforma!F12 -> 982748.03 | N8: =Proforma!G12 -> 229323.19 | O8: =Proforma!H12 -> 917292.76
C9: Expenses | D9: =Proforma!I46 -> 666645.79 | E9: =Proforma!J46 -> 686645.16 | F9: =Proforma!K46 -> 707244.52 | G9: =Proforma!L46 -> 728461.85 | H9: =Proforma!M46 -> 750315.71 | J9: =C9 -> Expenses | K9: =Proforma!D46 -> 495582.51 | L9: =Proforma!E46 -> 640708.76 | M9: =Proforma!F46 -> 682984.82 | N9: =Proforma!G46 -> 160680.77 | O9: =Proforma!H46 -> 642723.08
C11: Net Operating Income | D11: =D8-D9 -> 365854.21 | E11: =E8-E9 -> 378454.84 | F11: =F8-F9 -> 391773.48 | G11: =G8-G9 -> 405899.69 | H11: =H8-H9 -> 420939.28 | J11: =C11 -> Net Operating Income | K11: =K8-K9 -> 266803.39 | L11: =L8-L9 -> 257652.23 | M11: =M8-M9 -> 299763.21 | N11: =N8-N9 -> 68642.42 | O11: =O8-O9 -> 274569.68
J13: Excluded Expenses
J14: Owner HSA
J15: Owner Life Insurance
J16: Owner Salary
J17: Owner Vehicle
J18: Owner Storage Unit
J19: Owner Short Term Interst
J20: Owner Other Income
J21: Owner Mortgage Payment

Sheet Reimbursements
D1: Check | E1: Deposited to
A2: Earnest Money | B2: Cory 1031 Money
A3: Apprisal
A4: Inspection
A5: Environmental

Sheet Capital Stack
A1: Investor | B1: Amount | C1: Name/Entity | D1: Final Ownership | E1: Ownership | F1: Email | G1: Identifier | H1: Signed Docs | I1: Wire | J1: Both
D2: =E2*0.1 -> #DIV/0! | E2: =B2/$B$15 -> #DIV/0!
D3: =E3*0.1 -> #DIV/0! | E3: =B3/$B$15 -> #DIV/0!
D4: =E4*0.1 -> #DIV/0! | E4: =B4/$B$15 -> #DIV/0!
D5: =E5*0.1 -> #DIV/0! | E5: =B5/$B$15 -> #DIV/0!
D6: =E6*0.1 -> #DIV/0! | E6: =B6/$B$15 -> #DIV/0!
D7: =E7*0.1 -> #DIV/0! | E7: =B7/$B$15 -> #DIV/0!
D8: =E8*0.1 -> #DIV/0! | E8: =B8/$B$15 -> #DIV/0!
D9: =E9*0.1 -> #DIV/0! | E9: =B9/$B$15 -> #DIV/0!
D10: =E10*0.1 -> #DIV/0! | E10: =B10/$B$15 -> #DIV/0!
D11: =E11*0.1 -> #DIV/0! | E11: =B11/$B$15 -> #DIV/0!
D12: =E12*0.1 -> #DIV/0! | E12: =B12/$B$15 -> #DIV/0!
D13: 0.45
D14: 0.45
A15: Total | B15: =SUM(B2:B14) -> 0
A16: Remaining
A19: Reached out | C19: Followed up.
A20: Cam Cope | B20: Maybe | C20: 45222
A23: Bryan Griffiths | B23: Maybe | C23: 45222
A24: Alex Smith | B24: Maybe
A25: Randy Clayton
A27: Ben Clayton
A28: Jeff Meihoffer
A29: Rich Toloti | B29: Maybe
A30: Woody Klemetson
A31: Sterling Snow
A32: Blakely Cragun
A33: Adam and Andrew Law
A34: Ray Dodd
A35: Todd Orullian
A36: Adam Christensen
A37: Matt Boardman
A38: Scott Eliason
A39: Devin Deaton | B39: No
A40: Cameron Lee | B40: No
A41: Eric Motzkus | B41: No
A42: Aaron Meier | B42: No
A43: Mike Peterson | B43: No
A44: Jon Waddoups | B44: No
A45: Joel Reichert | B45: No
A46: Brad and Emily Forsyth | B46: No
A47: James Brewster | B47: No
A48: Lance Jorgenson | B48: No
A49: Dave Soper | B49: No
A51: Potential Others
A55: American Enterprises
A56: Jake Despain

Sheet Proforma
C2: 3 Year Historicals (Actuals)
C4: Year | D4: 2022 | E4: 2023 | F4: 2024 | G4: 2025 YTD (march) | H4: 2025 Annualized | I4: Proforma Year 1 | J4: Proforma Year 2 | K4: Proforma Year 3 | L4: Proforma Year 4 | M4: Proforma Year 5
C5: Potential Income | I5: =5000*20*12 -> 1200000 | J5: =I5*1.03 -> 1236000 | K5: =J5*1.03 -> 1273080 | L5: =K5*1.03 -> 1311272.4 | M5: =L5*1.03 -> 1350610.6
C6: Vacancy | I6: =-I5*0.15 -> -180000 | J6: =-J5*0.15 -> -185400 | K6: =-K5*0.15 -> -190962 | L6: =-L5*0.15 -> -196690.86 | M6: =-M5*0.15 -> -202591.59
C7: Income
C8: Day Care | I8: 5000 | J8: =I8*1.2 -> 6000 | K8: =J8*1.2 -> 7200 | L8: =K8*1.2 -> 8640 | M8: =L8*1.2 -> 10368
C9: Other Income | I9: 2500 | J9: =I9 -> 2500 | K9: =J9 -> 2500 | L9: =K9 -> 2500 | M9: =L9 -> 2500
C10: Rental Income | D10: 762385.9 | E10: 898360.99 | F10: 982748.03 | G10: 229323.19 | H10: =G10*4 -> 917292.76 | I10: =I5+I6 -> 1020000 | J10: =J5+J6 -> 1050600 | K10: =K5+K6 -> 1082118 | L10: =L5+L6 -> 1114581.5 | M10: =M5+M6 -> 1148019
C11: Move In Fees | I11: 5000 | J11: =I11*1.2 -> 6000 | K11: =J11*1.2 -> 7200 | L11: =K11*1.2 -> 8640 | M11: =L11*1.2 -> 10368
C12: Total Income | D12: =SUM(D8:D11) -> 762385.9 | E12: =SUM(E8:E11) -> 898360.99 | F12: =SUM(F8:F11) -> 982748.03 | G12: =SUM(G8:G11) -> 229323.19 | H12: =SUM(H8:H11) -> 917292.76 | I12: =SUM(I8:I11) -> 1032500 | J12: =SUM(J8:J11) -> 1065100 | K12: =SUM(K8:K11) -> 1099018 | ... M12: =SUM(M8:M11) -> 1171255 | O12: =I12*0.05 -> 51625 | P12: =55*4000 -> 220000 | Q12: =P12*12 -> 2640000 | R12: =Q12*0.95 -> 2508000 | S12: =R12*0.05 -> 125400
C14: Expenses
C15: Accounting | D15: $ - | E15: 1200 | F15: 11028.5 | G15: 1755 | H15: =G15*4 -> 7020 | I15: 8000 | J15: =I15*1.03 -> 8240 | K15: =J15*1.03 -> 8487.2 | L15: =K15*1.03 -> 8741.816 | M15: =L15*1.03 -> 9004.0705
C16: Advertising/Promotional | D16: 5965.18 | E16: 1525.14 | F16: 6522.48 | G16: 606.38 | H16: =G16*4 -> 2425.52 | I16: 6500 | J16: =I16*1.03 -> 6695 | K16: =J16*1.03 -> 6895.85 | L16: =K16*1.03 -> 7102.7255 | M16: =L16*1.03 -> 7315.8073
C17: Bank Charges | D17: 2 | E17: 1455.2 | F17: 1158.92 | G17: 75 | H17: =G17*4 -> 300 | I17: 1200 | J17: =I17*1.03 -> 1236 | K17: =J17*1.03 -> 1273.08 | L17: =K17*1.03 -> 1311.2724 | M17: =L17*1.03 -> 1350.6106
C18: Business licenses/Permits | D18: 2317 | E18: 2689 | F18: 829 | H18: =G18*4 -> 0 | I18: 2500 | J18: =I18*1.03 -> 2575 | K18: =J18*1.03 -> 2652.25 | L18: =K18*1.03 -> 2731.8175 | M18: =L18*1.03 -> 2813.772
C19: Nursing | D19: 3067.5 | E19: 3745 | F19: 4617.5 | G19: 957.5 | H19: =G19*4 -> 3830 | I19: 4500 | J19: =I19*1.03 -> 4635 | K19: =J19*1.03 -> 4774.05 | L19: =K19*1.03 -> 4917.2715 | M19: =L19*1.03 -> 5064.7896
C20: Dietician | H20: =G20*4 -> 0 | J20: =I20*1.03 -> 0 | K20: =J20*1.03 -> 0 | L20: =K20*1.03 -> 0 | M20: =L20*1.03 -> 0
C21: Dues & Subscriptions | D21: 1918.81 | E21: 1699.73 | F21: 5171.09 | G21: 1305.48 | H21: =G21*4 -> 5221.92 | I21: 2500 | J21: =I21*1.03 -> 2575 | K21: =J21*1.03 -> 2652.25 | L21: =K21*1.03 -> 2731.8175 | M21: =L21*1.03 -> 2813.772
C22: Administrator Expense | D22: 65000 | E22: 65000 | F22: 65000 | G22: =65000/4 -> 16250 | H22: =G22*4 -> 65000 | I22: 65000 | J22: =I22*1.03 -> 66950 | K22: =J22*1.03 -> 68958.5 | L22: =K22*1.03 -> 71027.255 | M22: =L22*1.03 -> 73158.073
C23: Employee Expenses | D23: =372150.03-D22+2021.49+179 -> 309350.52 | E23: =516817.64-E22+752.07+1162.79 -> 453732.5 | F23: =543985.31-F22+1707.34+100 -> 480792.65 | G23: =133613.48-G22+98.35 -> 117461.83 | H23: =G23*4 -> 469847.32 | I23: 450000 | J23: =I23*1.03 -> 463500 | K23: =J23*1.03 -> 477405 | L23: =K23*1.03 -> 491727.15 | M23: =L23*1.03 -> 506478.96
C24: Franchise Fees | H24: =G24*4 -> 0 | I24: 0 | J24: =I24*1.03 -> 0 | K24: =J24*1.03 -> 0 | L24: =K24*1.03 -> 0 | M24: =L24*1.03 -> 0 | T24: =10*50000 -> 500000
C25: Cleaning | H25: =G25*4 -> 0 | I25: 0 | J25: =I25*1.03 -> 0 | K25: =J25*1.03 -> 0 | L25: =K25*1.03 -> 0 | M25: =L25*1.03 -> 0 | T25: =125000*10 -> 1250000
C26: Household Supplies | D26: =8223.22+10820.73 -> 19043.95 | E26: =4866.29-13.35 -> 4852.94 | F26: =3711.27+1099.43 -> 4810.7 | G26: =699.96+277.55 -> 977.51 | H26: =G26*4 -> 3910.04 | I26: 5000 | J26: =I26*1.03 -> 5150 | K26: =J26*1.03 -> 5304.5 | L26: =K26*1.03 -> 5463.635 | M26: =L26*1.03 -> 5627.5441
C27: Management Fees | H27: =G27*4 -> 0 | I27: 0 | J27: =I27*1.03 -> 0 | K27: =J27*1.03 -> 0 | L27: =K27*1.03 -> 0 | M27: =L27*1.03 -> 0
C28: General business expenses | H28: =G28*4 -> 0 | I28: 0 | J28: =I28*1.03 -> 0 | K28: =J28*1.03 -> 0 | L28: =K28*1.03 -> 0 | M28: =L28*1.03 -> 0
C29: Insurance | D29: 1389.84 | E29: $ - | F29: 21949.61 | G29: 327 | H29: =G29*4 -> 1308 | I29: 21949.61 | J29: =I29*1.03 -> 22608.098 | K29: =J29*1.03 -> 23286.341 | L29: =K29*1.03 -> 23984.931 | M29: =L29*1.03 -> 24704.479
C30: Liability insurance | H30: =G30*4 -> 0 | J30: =I30*1.03 -> 0 | K30: =J30*1.03 -> 0 | L30: =K30*1.03 -> 0 | M30: =L30*1.03 -> 0
C31: Property insurance | H31: =G31*4 -> 0 | J31: =I31*1.03 -> 0 | K31: =J31*1.03 -> 0 | L31: =K31*1.03 -> 0 | M31: =L31*1.03 -> 0
C32: Lease Payments - Equipment | D32: 200 | F32: 783.82 | G32: 98.2 | H32: =G32*4 -> 392.8 | I32: 785 | J32: =I32*1.03 -> 808.55 | K32: =J32*1.03 -> 832.8065 | L32: =K32*1.03 -> 857.7907 | M32: =L32*1.03 -> 883.52442
C33: Medical Supplies | D33: 6602.89 | E33: 3349.16 | F33: 4064.08 | G33: 759.82 | H33: =G33*4 -> 3039.28 | I33: 4500 | J33: =I33*1.03 -> 4635 | K33: =J33*1.03 -> 4774.05 | L33: =K33*1.03 -> 4917.2715 | M33: =L33*1.03 -> 5064.7896
C34: Office expenses | D34: =43.3+950.68 -> 993.98 | E34: =161.88+27.49+659.21 -> 848.58 | F34: =744.4+99.66+25.86 -> 869.92 | G34: =1060.03+12.25+97.12 -> 1169.4 | H34: =G34*4 -> 4677.6 | I34: 1000 | J34: =I34*1.03 -> 1030 | K34: =J34*1.03 -> 1060.9 | L34: =K34*1.03 -> 1092.727 | M34: =L34*1.03 -> 1125.5088
C35: Operations Contract Service | D35: 1206.29 | E35: 1308 | F35: 1309.9 | G35: 426.2 | H35: =G35*4 -> 1704.8 | I35: 1500 | J35: =I35*1.03 -> 1545 | K35: =J35*1.03 -> 1591.35 | L35: =K35*1.03 -> 1639.0905 | M35: =L35*1.03 -> 1688.2632
C36: Placement Fees | H36: =G36*4 -> 0 | J36: =I36*1.03 -> 0 | K36: =J36*1.03 -> 0 | L36: =K36*1.03 -> 0 | M36: =L36*1.03 -> 0
C37: Raw Food | D37: 35749.36 | E37: 40486.08 | F37: 36303.32 | G37: 8753.37 | H37: =G37*4 -> 35013.48 | I37: 40000 | J37: =I37*1.03 -> 41200 | K37: =J37*1.03 -> 42436 | L37: =K37*1.03 -> 43709.08 | M37: =L37*1.03 -> 45020.352
C38: Repairs & maintenance | D38: 19962.91 | E38: =1110.41+8499.21 -> 9609.62 | F38: =1029.82+12540.51 -> 13570.33 | G38: =1196.79+1240.18 -> 2436.97 | H38: =G38*4 -> 9747.88 | I38: 15000 | J38: =I38*1.03 -> 15450 | K38: =J38*1.03 -> 15913.5 | L38: =K38*1.03 -> 16390.905 | M38: =L38*1.03 -> 16882.632
C39: Resident Activities | D39: 520.38 | E39: 903.39 | F39: 945.64 | G39: 169 | H39: =G39*4 -> 676 | I39: 2500 | J39: =I39*1.03 -> 2575 | K39: =J39*1.03 -> 2652.25 | L39: =K39*1.03 -> 2731.8175 | M39: =L39*1.03 -> 2813.772
C40: Taxes paid | D40: 830.29 | E40: 25122.8 | F40: 9.7 | H40: =G40*4 -> 0 | I40: 9711.18 | J40: =I40*1.03 -> 10002.515 | K40: =J40*1.03 -> 10302.591 | L40: =K40*1.03 -> 10611.669 | M40: =L40*1.03 -> 10930.019
C41: Property taxes | H41: =G41*4 -> 0 | J41: =I41*1.03 -> 0 | K41: =J41*1.03 -> 0 | L41: =K41*1.03 -> 0 | M41: =L41*1.03 -> 0
C42: Personal Property Taxes | H42: =G42*4 -> 0
C43: Travel/Vehicle | H43: =G43*4 -> 0 | J43: =I43*1.03 -> 0 | K43: =J43*1.03 -> 0 | L43: =K43*1.03 -> 0 | M43: =L43*1.03 -> 0
C44: Utilities | D44: 20822.61 | E44: 22200 | F44: 22898.16 | G44: 7152.11 | H44: =G44*4 -> 28608.44 | I44: 23000 | J44: =I44*1.03 -> 23690 | K44: =J44*1.03 -> 24400.7 | L44: =K44*1.03 -> 25132.721 | M44: =L44*1.03 -> 25886.703
C45: Misc Expense | D45: 639 | E45: 981.62 | F45: 349.5 | H45: =G45*4 -> 0 | I45: 1500 | J45: =I45*1.03 -> 1545 | K45: =J45*1.03 -> 1591.35 | L45: =K45*1.03 -> 1639.0905 | M45: =L45*1.03 -> 1688.2632
C46: Total Expenses | D46: =SUM(D15:D45) -> 495582.51 | E46: =SUM(E15:E45) -> 640708.76 | F46: =SUM(F15:F45) -> 682984.82 | G46: =SUM(G15:G45) -> 160680.77 | H46: =SUM(H15:H45) -> 642723.08 | I46: =SUM(I15:I45) -> 666645.79 | J46: =SUM(J15:J45) -> 686645.16 | K46: =SUM(K15:K45) -> 707244.52 | ... M46: =SUM(M15:M45) -> 750315.71
C47: Net Operating Income | D47: =D12-D46 -> 266803.39 | E47: =E12-E46 -> 257652.23 | F47: =F12-F46 -> 299763.21 | G47: =G12-G46 -> 68642.42 | H47: =H12-H46 -> 274569.68 | I47: =I12-I46 -> 365854.21 | J47: =J12-J46 -> 378454.84 | K47: =K12-K46 -> 391773.48 | ... M47: =M12-M46 -> 420939.28 | O47: =I47/12 -> 30487.851 | P47: =O47*4 -> 121951.4
C49: Cap Rate | D49: =D47/'Deal Overview'!$C$5 -> 0.083376059 | E49: =E47/'Deal Overview'!$C$5 -> 0.080516322 | F49: =F47/'Deal Overview'!$C$5 -> 0.093676003 | G49: =G47/'Deal Overview'!$C$5 -> 0.021450756 | H49: =H47/'Deal Overview'!$C$5 -> 0.085803025 | I49: =I47/'Deal Overview'!$C$5 -> 0.11432944 | J49: =J47/'Deal Overview'!$C$5 -> 0.11826714 | K49: =K47/'Deal Overview'!$C$5 -> 0.12242921 | ... M49: =M47/'Deal Overview'!$C$5 -> 0.13154352
C50: Expense Ratio
C51: Misc Unforseen/Reserves | I51: =I12*0.05 -> 51625 | J51: =I51 -> 51625 | K51: =J51 -> 51625 | L51: =K51 -> 51625 | M51: =L51 -> 51625 | O51: =I12-I46-I51-I53-I54 -> 293579.21
C52: Mortgage | F52: =F47/I52 -> 1.5163214 | I52: ='Sources and Uses'!J9 -> 197691.07 | J52: =I52 -> 197691.07 | K52: =J52 -> 197691.07 | L52: =K52 -> 197691.07 | M52: =L52 -> 197691.07 | O52: =O51-I52 -> 95888.139 | R52: ='Sources and Uses'!D13 -> 1240000
C53: Asset Management Fees | I53: =I12*0.01 -> 10325 | J53: =J12*0.01 -> 10651 | K53: =K12*0.01 -> 10990.18 | L53: =L12*0.01 -> 11343.615 | M53: =M12*0.01 -> 11712.55
C54: Management Fees | I54: =I12*0.01 -> 10325 | J54: =J12*0.01 -> 10651 | K54: =K12*0.01 -> 10990.18 | L54: =L12*0.01 -> 11343.615 | M54: =M12*0.01 -> 11712.55
C55: Net Cash Fow | I55: =I47-I51-I52-I53-I54 -> 95888.139 | J55: =J47-J51-J52-J53-J54 -> 107836.77 | K55: =K47-K51-K52-K53-K54 -> 120477.05 | L55: =L47-L51-L52-L53-L54 -> 133896.38 | M55: =M47-M51-M52-M53-M54 -> 148198.11
C56: Return | D56: =D55/'Deal Overview'!$C$8 -> 0 | E56: =E55/'Deal Overview'!$C$8 -> 0 | F56: =F55/'Deal Overview'!$C$8 -> 0 | G56: =G55/'Deal Overview'!$C$8 -> 0 | H56: =H55/'Deal Overview'!$C$8 -> 0 | I56: =I55/'Sources and Uses'!$D$13 -> 0.077329144 | J56: =J55/'Deal Overview'!$C$8 -> 0.086965133 | K56: =K55/'Deal Overview'!$C$8 -> 0.097158912 | L56: =L55/'Deal Overview'!$C$8 -> 0.10798096 | M56: =M55/'Deal Overview'!$C$8 -> 0.1195146 | O56: =I51+I53+I54 -> 72275
C57: Principal Reduction | I57: ='Sources and Uses'!L8 -> Total Principal Reduction | J57: ='Sources and Uses'!M8 -> -34799.016 | K57: ='Sources and Uses'!N8 -> -37351.755 | L57: ='Sources and Uses'!O8 -> -40091.754 | M57: ='Sources and Uses'!P8 -> -43032.75
C58: Loan Balance | I58: ='Sources and Uses'!M9 -> 2275201 | J58: ='Sources and Uses'!N9 -> 2237849.2 | K58: ='Sources and Uses'!O9 -> 2197757.5 | L58: ='Sources and Uses'!P9 -> 2154724.7 | M58: ='Sources and Uses'!Q9 -> 2108535.2
C59: Sale Price | I59: =I47/0.08 -> 4573177.6 | J59: =J47/0.08 -> 4730685.5 | K59: =K47/0.08 -> 4897168.5 | L59: =L47/0.08 -> 5073746.1 | M59: =M47/0.08 -> 5261741
C60: Sale Costs | I60: =I59*0.06 -> 274390.66 | J60: =J59*0.06 -> 283841.13 | K60: =K59*0.06 -> 293830.11 | L60: =L59*0.06 -> 304424.76 | M60: =M59*0.06 -> 315704.46 | P60: =I55+I52 -> 293579.21
C61: Net Proceeds | I61: =I59-I60-I58 -> 2023586 | J61: =J59-J60-J58 -> 2208995.1 | K61: =K59-K60-K58 -> 2405580.9 | L61: =L59-L60-L58 -> 2614596.6 | M61: =M59-M60-M58 -> 2837501.3
C62: Investor Preferred Return | D62: 0.08 | I62: ='Sources and Uses'!$D$13*$D$62 -> 99200 | J62: ='Sources and Uses'!$D$13*$D$62 -> 99200 | K62: ='Sources and Uses'!$D$13*$D$62 -> 99200 | L62: ='Sources and Uses'!$D$13*$D$62 -> 99200 | M62: ='Sources and Uses'!$D$13*$D$62 -> 99200
C63: Sponsor Split | D63: 0.5 | I63: =if((I55-I62)>0,(I55-I62)/2,0) -> 0 | J63: =if((J55-J62)>0,(J55-J62)/2,0) -> 4318.3827 | K63: =if((K55-K62)>0,(K55-K62)/2,0) -> 10638.525 | L63: =if((L55-L62)>0,(L55-L62)/2,0) -> 17348.192 | M63: =if((M55-M62)>0,(M55-M62)/2,0) -> 24499.053
C64: Net Estimated Annual Cash Flow to Investors | I64: =I55-I63 -> 95888.139 | J64: =J55-J63 -> 103518.38 | K64: =K55-K63 -> 109838.53 | L64: =L55-L63 -> 116548.19 | M64: =M55-M63 -> 123699.05
C65: Estimated Return to Investors | I65: =I64/'Sources and Uses'!$D$13 -> 0.077329144 | J65: =J64/'Sources and Uses'!$D$13 -> 0.083482567 | K65: =K64/'Sources and Uses'!$D$13 -> 0.088579456 | L65: =L64/'Sources and Uses'!$D$13 -> 0.093990477 | M65: =M64/'Sources and Uses'!$D$13 -> 0.099757301
C67: Total Sponsor Fees
C68: Cash flow Promote | I68: =I63 -> 0 | J68: =J63 -> 4318.3827 | K68: =K63 -> 10638.525 | L68: =L63 -> 17348.192 | M68: =M63 -> 24499.053
C69: Disposition Fees if we sell | M69: =M59*0.03 -> 157852.23
C70: Loan Fees | I70: ='Sources and Uses'!D18 -> 23100
C71: Asset Management Fees | I71: =I53 -> 10325 | J71: =J53 -> 10651 | K71: =K53 -> 10990.18 | L71: =L53 -> 11343.615 | M71: =M53 -> 11712.55
C72: Promote on Sale | M72: =(M61-'Sources and Uses'!D13)*D63 -> 798750.63
C73: Total Fees | D73: =sum(I68:M72) -> 1091529.4 | I73: =I47-I52 -> 168163.14
H78: DO NOT DELETE THESE | I78: =I47 -> 365854.21 | J78: =J47 -> 378454.84 | K78: =K47 -> 391773.48 | L78: =L47 -> 405899.69 | M78: =M47 -> 420939.28
H79: DO NOT DELETE THESE | I79: =I52 -> 197691.07 | J79: =J52 -> 197691.07 | K79: =K52 -> 197691.07 | L79: =L52 -> 197691.07 | M79: =M52 -> 197691.07
H86: Monthly NOI | I86: =I47/12 -> 30487.851 | O86: Total Cash Flow | P86: =sum(I55:M55) -> 606296.44
H87: Monthly Mortgage | I87: =I52/12 -> 16474.256 | O87: Total Profit at Sale | P87: =M61-'Sources and Uses'!D13 -> 1597501.3
D88: =D46+D89 -> 573340 | E88: =E46+E89 -> 735899.49 | F88: =F46+F89 -> 902341.41 | G88: =G46+G89 -> 217731.82 | H88: Monthly Cash Flow Estimate | I88: =I55/12 -> 7990.6783 | O88: Total | P88: =P87+P86 -> 2203797.7
C89: Expenses Removed | D89: =SUM(D90:D1048604) -> 77757.49 | E89: =SUM(E90:#REF!) -> 95190.73 | F89: =SUM(F90:#REF!) -> 219356.59 | G89: =SUM(G90:#REF!) -> 57051.05 | O89: Total Investor Pref | P89: =sum(I62:M62) -> 496000
C90: Related Party Rent | D90: 76200 | E90: 94500 | F90: 216146.09 | G90: 55000 | O90: Net to Split | P90: =P88-P89 -> 1707797.7
C91: Owner Meals | D91: 302.63 | E91: 267.59 | F91: 924.19 | G91: 26.68 | O91: Sponsor | P91: =P90/2 -> 853898.85
C92: Owner Travel | D92: 844.33 | E92: $ - | F92: 1269.69 | O92: Investor Total | P92: =P91+P89 -> 1349898.9
C93: Vehicle Expense | D93: 410.53 | E93: 423.14 | F93: 310 | P93: =P92/'Sources and Uses'!D13 -> 1.0886281
C94: Interest Expense | D94: $ - | E94: $ - | F94: 693.1 | G94: 1471.87
C95: Other Income | D95: $ - | E95: $ - | F95: 13.52
G96: 552.5 | P96: Year 0 | Q96: Year 1 | R96: Year 2 | S96: Year 3 | T96: Year 4 | U96: Year 5
O97: Cash Flow | P97: =-'Sources and Uses'!D13 -> -1240000 | Q97: =I55 -> 95888.139 | R97: =J55 -> 107836.77 | S97: =K55 -> 120477.05 | T97: =L55 -> 133896.38 | U97: =M55 -> 148198.11
O98: Principal Reduction
O99: Net Proceeds from Sale | U99: =M61 -> 2837501.3
O100: Sponsor Share | Q100: =(I55-I62)/2 -> -1655.9304 | R100: =(J55-J62)/2 -> 4318.3827 | S100: =(K55-K62)/2 -> 10638.525 | T100: =(L55-L62)/2 -> 17348.192 | U100: =((M55-M62)/2)+((U99-'Sources and Uses'!D13)/2) -> 823249.68
O101: Total to Investor | P101: =P99+P98+P97 -> -1240000 | Q101: =Q99+Q98+Q97-Q100 -> 97544.07 | R101: =R99+R98+R97-R100 -> 103518.38 | S101: =S99+S98+S97-S100 -> 109838.53 | T101: =T99+T98+T97-T100 -> 116548.19 | U101: =U99+U98+U97-U100 -> 2162449.7
O102: Irr | P102: =irr(P101:U101) -> 0.17765319
O103: Total Return | P103: =sum(P101:U101)/'Sources and Uses'!D13 -> 1.0886281
P106: Year 0 | Q106: Year 1 | R106: Year 2 | S106: Year 3 | T106: Year 4 | U106: Year 5
O107: Cash Flow | P107: =P97 -> -1240000 | Q107: =Q97 -> 95888.139 | R107: =R97 -> 107836.77 | S107: =K65 -> 0.088579456 | T107: =L65 -> 0.093990477 | U107: =M65 -> 0.099757301
O108: Principal Reduction
O109: Net Proceeds from Sale | R109: =J61 -> 2208995.1 | U109: =M91
O110: Sponsor Share | Q110: =Q100 -> -1655.9304 | R110: =R100 -> 4318.3827 | S110: =(K65-K92)/2 -> 0.044289728 | T110: =(L65-L92)/2 -> 0.046995239 | U110: =((M65-M92)/2)+((U109-'Sources and Uses'!D23)/2) -> -108874.95
O111: Total to Investor | P111: =P109+P108+P107 -> -1240000 | Q111: =Q109+Q108+Q107-Q110 -> 97544.07 | R111: =R109+R108+R107-R110 -> 2312513.5 | S111: =S109+S108+S107-S110 -> 0.044289728 | T111: =T109+T108+T107-T110 -> 0.046995239 | U111: =U109+U108+U107-U110 -> 108875.05
O112: Irr | P112: =irr(P111:U111) -> 0.4167763
O113: Total Return
O118: Waterfall | P118: Year 0 | Q118: Year 1 | R118: Year 2 | S118: Year 3 | T118: Year 4 | U118: Year 5 | V118: Total
O119: Cash Flow | P119: =-'Sources and Uses'!G20 -> -1240000 | Q119: =I55 -> 95888.139 | R119: =J55 -> 107836.77 | S119: =K55 -> 120477.05 | T119: =L55 -> 133896.38 | U119: =M55 -> 148198.11 | V119: =SUM(P119:U119) -> -633703.56
N120: 0.08 | O120: Preferred Return | P120: =-P119*$N$120 -> 99200 | Q120: =P120 -> 99200 | R120: =Q120 -> 99200 | S120: =R120 -> 99200 | T120: =S120 -> 99200 | U120: =T120 -> 99200 | V120: =SUM(P120:U120) -> 595200
O121: Net Proceeds from Sale | U121: =M61 -> 2837501.3 | V121: =SUM(P121:U121) -> 2837501.3
...
