Workbook

Sheet Deal Overview
B2: Deal Summary | F2: Sensitivity Analysis
B4: Cost Summary | C4: Cost | F4: Scenarios >>> | G4: Disappointed | H4: Conservative | I4: Expected | J4: Aggressive
B5: Purchase Price | C5: ='Sources and Uses'!D5 -> 6500000 | F5: Gross Potential Rent | G5: =H5 | H5: =I5 | I5: =Proforma!I5 | J5: =I5
B6: ='Sources and Uses'!B9 -> Total Debt | C6: ='Sources and Uses'!D9 -> 4550000 | F6: Vacancy | G6: =H6*1.05 -> 0 | H6: =I6*1.05 -> 0 | I6: =Proforma!I6 | J6: =-J5*0.1 -> 0
B7: Total Fees | C7: ='Sources and Uses'!D23 -> 461500 | F7: Other Income
B8: Total Equity | C8: ='Sources and Uses'!G20 -> 2541500 | F8: Effective Gross Income | G8: =G7+G6+G5 -> 0 | H8: =H7+H6+H5 -> 0 | I8: =Proforma!I12 -> 1462597.9 | J8: =J7+J6+J5 -> 0
B9: Reserve | C9: ='Sources and Uses'!G19 -> 130000 | F9: Expenses | G9: =H9 -> 804185 | H9: =I9 -> 804185 | I9: =Proforma!I46 -> 804185 | J9: =I9*0.9 -> 723766.5
B10: Total Cost | C10: =C5+C7+C9 -> 7091500 | F10: Management Fees 3rd Party | G10: =H10 -> 29251.957 | H10: =I10 -> 29251.957 | I10: =Proforma!I54 -> 29251.957 | J10: =I10 -> 29251.957
F11: Vega Asset Management Fees | G11: =H11 -> 14625.979 | H11: =I11 -> 14625.979 | I11: =Proforma!I53 -> 14625.979 | J11: =I11 -> 14625.979
B12: Total | C12: $ | D12: % | F12: Misc Unexpected Expense Reserve | G12: =H12 -> 20000 | H12: =I12 -> 20000 | I12: =Proforma!I51 -> 20000 | J12: =I12 -> 20000
B13: Equity | C13: =C8 -> 2541500 | D13: =C13/C15 -> 0.3583868 | F13: Net Operating Income | G13: =G8-G9-G10-G11-G12 -> -868062.94 | H13: =H8-H9-H10-H11-H12 -> -868062.94 | I13: =I8-I9-I10-I11-I12 -> 594534.93 | J13: =J8-J9-J10-J11-J12 -> -787644.44
B14: Debt | C14: =C6 -> 4550000 | D14: =C14/C15 -> 0.6416132
B15: Total Required Capital From All Sources | C15: =C14+C13 -> 7091500 | D15: =SUM(D13:D14) -> 1 | F15: Annual Payment | G15: ='Sources and Uses'!$J$9 -> 370370.81 | H15: ='Sources and Uses'!$J$9 -> 370370.81 | I15: ='Sources and Uses'!$J$9 -> 370370.81 | J15: ='Sources and Uses'!$J$9 -> 370370.81
F16: Cash Flow | G16: =G13-G15 -> -1238433.7 | H16: =H13-H15 -> -1238433.7 | I16: =I13-I15 -> 224164.12 | J16: =J13-J15 -> -1158015.2
B17: Total | D17: % | F17: Investor Pref | G17: =H17 -> 203320 | H17: =I17 -> 203320 | I17: =D18*'Sources and Uses'!D13 -> 203320 | J17: =I17 -> 203320
B18: Investor Pref | D18: 0.08 | F18: Remaining | G18: =if((G16-G17)>0,G16-G17,"") | H18: =if((H16-H17)>0,H16-H17,"") | I18: =if((I16-I17)>0,I16-I17,"") -> 20844.125 | J18: =if((J16-J17)>0,J16-J17,"")
B19: Sponsor Promote | C19: =C11 | D19: 0.5 | F19: Investor Split | G19: =G18/2 -> 0 | H19: =H18/2 -> 0 | I19: =I18/2 -> 10422.062 | J19: =J18/2 -> 0
F20: Sponsor Split | G20: =G19 -> 0 | H20: =H19 -> 0 | I20: =I19 -> 10422.062 | J20: =J19 -> 0
F21: Total Investor Cash Flow Upon Stabilization | G21: =if((G16-G17)>0,G19+G17,G16) -> -1238433.7 | H21: =if((H16-H17)>0,H19+H17,H16) -> -1238433.7 | I21: =if((I16-I17)>0,I19+I17,I16) -> 213742.06 | J21: =if((J16-J17)>0,J19+J17,J16) -> -1158015.2
F22: 1st Year Cash on Cash | G22: =G21/'Sources and Uses'!$D$13 -> -0.48728457 | H22: =H21/'Sources and Uses'!$D$13 -> -0.48728457 | I22: =I21/'Sources and Uses'!$D$13 -> 0.084100752 | J22: =J21/'Sources and Uses'!$D$13 -> -0.45564243
F23: 1st Year Principal Reduction | G23: =H23 -> 0.029336099 | H23: =I23 -> 0.029336099 | I23: =-'Sources and Uses'!M8/'Sources and Uses'!D13 -> 0.029336099 | J23: =I23 -> 0.029336099
F24: Total 1st Year benefit | G24: =G23+G22 -> -0.45794847 | H24: =H23+H22 -> -0.45794847 | I24: =I23+I22 -> 0.11343685 | J24: =J23+J22 -> -0.42630633

Sheet Sources and Uses
B2: Sources and Uses of Funds
B4: Acquisition Assumptions | F4: Lender | G4: Amount | H4: Interest Rate | I4: Term | J4: Monthly Payment | L4: Principal Reduction | M4: Year 1 | N4: Year 2 | O4: Year 3 | P4: Year 4 | Q4: Year 5
B5: Total Project Cost | D5: 6500000 | F5: 1st Position | G5: =D6 -> 4550000 | H5: 0.0655 | I5: 25 | J5: =PMT(H5/12,I5*12,-G5,0,0) -> 30864.234 | M5: =iferror(CUMPRINC(H5/12,I5*12,G5,1,12,0),"") -> -74557.694 | N5: =iferror(CUMPRINC(H5/12,I5*12,G5,13,24,0),"") -> -79590.531 | O5: =iferror(CUMPRINC(H5/12,I5*12,G5,25,36,0),"") -> -84963.098 | P5: =iferror(CUMPRINC(H5/12,I5*12,G5,37,48,0),"") -> -90698.327 | Q5: =iferror(CUMPRINC(H5/12,I5*12,G5,49,60,0),"") -> -96820.698
B6: 1st Position Loan (Bank) | C6: 0.7 | D6: =C6*D5 -> 4550000 | F6: 2nd Position | G6: =D7 -> 0 | H6: 0.05 | I6: 25 | J6: =PMT(H6/12,I6*12,-G6,0,1) -> 0 | M6: =iferror(CUMPRINC(H6/12,I6*12,G6,1,12,0),"") | N6: =iferror(CUMPRINC(H6/12,I6*12,G6,13,24,0),"") | O6: =iferror(CUMPRINC(H6/12,I6*12,G6,25,36,0),"") | P6: =iferror(CUMPRINC(H6/12,I6*12,G6,37,48,0),"") | Q6: =iferror(CUMPRINC(H6/12,I6*12,G6,49,60,0),"")
B7: 2nd Position Loan (SBA) | C7: 0 | D7: =C7*D5 -> 0 | F7: Seller | G7: =D8 -> 0 | H7: 0.05 | I7: 25 | J7: =PMT(H7/12,I7*12,-G7,0,1) -> 0 | M7: =iferror(CUMPRINC(H7/12,I7*12,G7,1,12,0),"") | N7: =iferror(CUMPRINC(H7/12,I7*12,G7,13,24,0),"") | O7: =iferror(CUMPRINC(H7/12,I7*12,G7,25,36,0),"") | P7: =iferror(CUMPRINC(H7/12,I7*12,G7,37,48,0),"") | Q7: =iferror(CUMPRINC(H7/12,I7*12,G7,49,60,0),"")
B8: 3rd Position Seller Finance | C8: 0 | D8: =C8*D5 -> 0 | F8: Total | G8: =G6+G5+G7 -> 4550000 | I8: Monthly Debt Service | J8: =J6+J5+J7 -> 30864.234 | L8: Total Principal Reduction | M8: =sum(M5:M7) -> -74557.694 | N8: =sum(N5:N7) -> -79590.531 | O8: =sum(O5:O7) -> -84963.098 | P8: =sum(P5:P7) -> -90698.327 | Q8: =sum(Q5:Q7) -> -96820.698
B9: Total Debt | D9: =D8+D7+D6 -> 4550000 | I9: Annual Debt Service | J9: =J8*12 -> 370370.81 | L9: Loan Balance | M9: =G8+M8 -> 4475442.3 | N9: =N8+M9 -> 4395851.8 | O9: =O8+N9 -> 4310888.7 | P9: =P8+O9 -> 4220190.3 | Q9: =Q8+P9 -> 4123369.7
B10: Down Payment | D10: =D5-D6-D7-D8 -> 1950000 | F10: Excess Land Value | G10: 0
B11: Reserve | C11: 0.02 | D11: =D5*C11 -> 130000 | G11: =Proforma!I56 -> 0.088201505
B12: Fees | D12: =D23 -> 461500
B13: Total Equity | D13: =D12+D11+D10 -> 2541500 | J13: =415000/680000 -> 0.61029412
B14: Total Sources and Uses | D14: =D13+D9 -> 7091500 | J14: =680000/415000 -> 1.6385542
B16: Fees | F16: Sources and Uses of Funds
B17: Bank Fees | C17: 0.02 | D17: =C17*D9 -> 91000 | F17: Bank Required Down Payment | G17: =D10 -> 1950000
B18: Vega Capital Markets Fee | C18: 0.01 | D18: =C18*D9 -> 45500 | F18: Fees | G18: =D23 -> 461500
B19: Acquisition Fee | C19: 0.03 | D19: =C19*D5 -> 195000 | F19: Reserve | G19: =D11 -> 130000
B20: Due Diligence Costs | C20: 0.01 | D20: =C20*D5 -> 65000 | F20: Total | G20: =SUM(G17:G19) -> 2541500
B21: Closing Costs | C21: 0.01 | D21: =C21*D5 -> 65000 | O21: =Proforma!I12 -> 1462597.9
B23: Total | D23: =SUM(D17:D22) -> 461500
G49: TIC Agreement | H49: Closing Docs | J49: Fund II ***8204
B50: Journal Entry 1 - Acquisition fees | F50: Ownership | G50: Ownership | H50: Equity | I50: Current Funds | J50: Transfer
B51: Account | C51: Debits | D51: Credits | F51: Fund II - Vega Hearthstone AL LLC | G51: 0.796 | H51: =G51*$G$20 -> 2023034 | I51: =G72 -> 1794224.6 | J51: =H51-I51 -> 228809.35
B52: Acqusiition Fees | C52: =D19 -> 195000 | F52: Phillip Chipping | G52: 0.1673 | H52: =G52*$G$20 -> 425192.95
B53: Capital From Vega Assisted Living Fund II, LP | D53: =C52 -> 195000 | F53: Hearthstone Personal Holdings LLC | G53: 0.0367 | H53: =G53*$G$20 -> 93273.05
B54: Total | C54: =C53+C52 -> 195000 | D54: =D53+D52 -> 195000 | H54: =G54*$G$20 -> 0
F55: Total | G55: =sum(G51:G54) -> 1 | H55: =sum(H51:H54) -> 2541500
B56: Journal Entry 2 - Building/Mortgages
B57: Account | C57: Debits | D57: Credits
B58: Buildings | C58: =6500000-C59 -> 5663000
B59: Land | C59: 837000
B60: Mortgages | D60: 4522000
B61: Capital from Vega Assisted Living Fund II, LP | D61: 20000
B62: Capital from Phillip Chipping | D62: 425225
B63: Capital from Hearthstone Personal Holdings | D63: 92791
B64: Capital from Vega Assisted Living Fund II, LP | D64: 1503225.6 | F64: =1189683.44+305737.71 -> 1495421.1
B65: Inspections | C65: 999
B66: Capital from vega Assisted Living Fund II, LP | D66: 999
B67: Closing Costs | C67: =3238.17+5400+900+45220+811.48+15+55+607+225+35+6070+450+50+165 -> 63241.65
B68: Total | C68: =sum(C58:C67) -> 6564240.7 | D68: =sum(D58:D67) -> 6564240.7
B70: Fund II Journal Entry - Credit from Vega Property Holdings LLC
B71: Account | C71: Debits | D71: Credits | F71: Balance Sheet | G71: 46048
B72: LP Capital Contributions | C72: =D37 | D72: 195000 | F72: Funds in Property Balance Sheet from Fund II | G72: 1794224.6
B73: Vega Sandy City AL LLC | C73: 195000 | F73: Funds in Fund Balance Sheet for Property | G73: 1711420.1
B74: Total | C74: =C73+C72 -> 195000 | D74: =D73+D72 -> 195000
B76: Loan Consulting Fee Paid to Vega Capital Markets LLC
B77: Paid - transferred on | C77: 45683 | D77: 45220
B79: Mortgage Principale (deleted) on P&L | C79: 5991.42

Sheet Proforma
C2: 3 Year Historicals (Actuals)
C4: Year | D4: 2022 | E4: 2023 | F4: 2024 | G4: 2025 YTD (May) | H4: 2025 Annualized | I4: Proforma Year 1 | J4: Proforma Year 2 | K4: Proforma Year 3 | L4: Proforma Year 4 | M4: Proforma Year 5
C5: Potential Income
C6: Vacancy
C7: Income
C8: Day Care
C9: Other Income
C10: Rental Income | D10: 1192301.8 | E10: 1362380.8 | F10: 1419997.9 | G10: 591056.02 | H10: =(G10/5)*12 -> 1418534.4 | I10: =F10*1.03 -> 1462597.9 | J10: =I10*1.03 -> 1506475.8 | K10: =J10*1.03 -> 1551670.1 | L10: =K10*1.03 -> 1598220.2 | M10: =L10*1.03 -> 1646166.8
C11: Move In Fees | N11: =N12-I12 -> -47185.868
C12: Total Income | D12: =SUM(D8:D11) -> 1192301.8 | E12: =SUM(E8:E11) -> 1362380.8 | F12: =SUM(F8:F11) -> 1419997.9 | G12: =SUM(G8:G11) -> 591056.02 | H12: =SUM(H8:H11) -> 1418534.4 | I12: =SUM(I8:I11) -> 1462597.9 | J12: =SUM(J8:J11) -> 1506475.8 | K12: =SUM(K8:K11) -> 1551670.1 | ... M12: =SUM(M8:M11) -> 1646166.8 | N12: =N13*12 -> 1415412
I13: =I12/12 -> 121883.16 | N13: 117951
C14: Expenses
C15: Accounting | D15: 15460.04 | E15: 26572.43 | F15: 19885.46 | G15: 11621.81 | H15: =(G15/5)*12 -> 27892.344 | I15: 6000 | J15: =I15*1.03 -> 6180 | K15: =J15*1.03 -> 6365.4 | L15: =K15*1.03 -> 6556.362 | M15: =L15*1.03 -> 6753.0529
C16: Advertising/Promotional | D16: 4574.69 | E16: 1840.1 | F16: 756.99 | G16: 552.81 | H16: =(G16/5)*12 -> 1326.744 | I16: 1000 | J16: =I16*1.03 -> 1030 | K16: =J16*1.03 -> 1060.9 | L16: =K16*1.03 -> 1092.727 | M16: =L16*1.03 -> 1125.5088
C17: Bank Charges | D17: 12 | E17: 35 | F17: 114 | G17: 47.5 | H17: =(G17/5)*12 -> 114 | I17: 150 | J17: =I17*1.03 -> 154.5 | K17: =J17*1.03 -> 159.135 | L17: =K17*1.03 -> 163.90905 | M17: =L17*1.03 -> 168.82632
C18: Business licenses/Permits | J18: =I18*1.03 -> 0 | K18: =J18*1.03 -> 0 | L18: =K18*1.03 -> 0 | M18: =L18*1.03 -> 0
C19: Nursing | J19: =I19*1.03 -> 0 | K19: =J19*1.03 -> 0 | L19: =K19*1.03 -> 0 | M19: =L19*1.03 -> 0
C20: Dietician | J20: =I20*1.03 -> 0 | K20: =J20*1.03 -> 0 | L20: =K20*1.03 -> 0 | M20: =L20*1.03 -> 0
C21: Dues & Subscriptions | J21: =I21*1.03 -> 0 | K21: =J21*1.03 -> 0 | L21: =K21*1.03 -> 0 | M21: =L21*1.03 -> 0
C22: Administrator Expense | I22: 32500 | J22: =I22*1.03 -> 33475 | K22: =J22*1.03 -> 34479.25 | L22: =K22*1.03 -> 35513.628 | M22: =L22*1.03 -> 36579.036
C23: Employee Expenses | D23: 501391.38 | E23: 541536.51 | F23: 538511.73 | G23: 205391.66 | H23: =(G23/5)*12 -> 492939.98 | I23: 505280 | J23: =I23*1.03 -> 520438.4 | K23: =J23*1.03 -> 536051.55 | L23: =K23*1.03 -> 552133.1 | M23: =L23*1.03 -> 568697.09 | N23: =I23/12 -> 42106.667
C24: Franchise Fees | J24: =I24*1.03 -> 0 | K24: =J24*1.03 -> 0 | L24: =K24*1.03 -> 0 | M24: =L24*1.03 -> 0
C25: Cleaning | D25: 13840.68 | E25: 18500.17 | F25: 20292.41 | G25: 6410 | H25: =(G25/5)*12 -> 15384 | I25: 20000 | J25: =I25*1.03 -> 20600 | K25: =J25*1.03 -> 21218 | L25: =K25*1.03 -> 21854.54 | M25: =L25*1.03 -> 22510.176
C26: Household Supplies | J26: =I26*1.03 -> 0 | K26: =J26*1.03 -> 0 | L26: =K26*1.03 -> 0 | M26: =L26*1.03 -> 0
C27: Management Fees | J27: =I27*1.03 -> 0 | K27: =J27*1.03 -> 0 | L27: =K27*1.03 -> 0 | M27: =L27*1.03 -> 0
C28: General business expenses | D28: 5687.18 | E28: 830.86 | F28: 1060.34 | G28: 174.4 | H28: =(G28/5)*12 -> 418.56 | J28: =I28*1.03 -> 0 | K28: =J28*1.03 -> 0 | L28: =K28*1.03 -> 0 | M28: =L28*1.03 -> 0
C29: Insurance | D29: 29254.9 | E29: 26381.79 | F29: 26603.22 | G29: 22932.14 | H29: =(G29/5)*12 -> 55037.136 | I29: 25000 | J29: =I29*1.03 -> 25750 | K29: =J29*1.03 -> 26522.5 | L29: =K29*1.03 -> 27318.175 | M29: =L29*1.03 -> 28137.72
C30: Liability insurance | J30: =I30*1.03 -> 0 | K30: =J30*1.03 -> 0 | L30: =K30*1.03 -> 0 | M30: =L30*1.03 -> 0
C31: Property insurance | J31: =I31*1.03 -> 0 | K31: =J31*1.03 -> 0 | L31: =K31*1.03 -> 0 | M31: =L31*1.03 -> 0
C32: Lease Payments - Equipment | J32: =I32*1.03 -> 0 | K32: =J32*1.03 -> 0 | L32: =K32*1.03 -> 0 | M32: =L32*1.03 -> 0
C33: Medical Supplies | D33: 3105.6 | E33: 3294.62 | F33: 3512.6 | G33: 627.65 | H33: =(G33/5)*12 -> 1506.36 | I33: 3555 | J33: =I33*1.03 -> 3661.65 | K33: =J33*1.03 -> 3771.4995 | L33: =K33*1.03 -> 3884.6445 | M33: =L33*1.03 -> 4001.1838
C34: Office expenses | D34: 1325.14 | E34: 2418.49 | F34: 2654.9 | G34: 1096.27 | H34: =(G34/5)*12 -> 2631.048 | I34: 2500 | J34: =I34*1.03 -> 2575 | K34: =J34*1.03 -> 2652.25 | L34: =K34*1.03 -> 2731.8175 | M34: =L34*1.03 -> 2813.772
C35: Operations Contract Service | J35: =I35*1.03 -> 0 | K35: =J35*1.03 -> 0 | L35: =K35*1.03 -> 0 | M35: =L35*1.03 -> 0
C36: Placement Fees | J36: =I36*1.03 -> 0 | K36: =J36*1.03 -> 0 | L36: =K36*1.03 -> 0 | M36: =L36*1.03 -> 0
C37: Raw Food | D37: 77567.84 | E37: 88930.57 | F37: 107637.74 | G37: 43498.28 | H37: =(G37/5)*12 -> 104395.87 | I37: 110000 | J37: =I37*1.03 -> 113300 | K37: =J37*1.03 -> 116699 | L37: =K37*1.03 -> 120199.97 | M37: =L37*1.03 -> 123805.97
C38: Repairs & maintenance | D38: 28715.97 | E38: 27473.47 | F38: 26877.55 | G38: 51174.03 | H38: =(G38/5)*12 -> 122817.67 | I38: 25000 | J38: =I38*1.03 -> 25750 | K38: =J38*1.03 -> 26522.5 | L38: =K38*1.03 -> 27318.175 | M38: =L38*1.03 -> 28137.72
C39: Resident Activities | D39: 3440.63 | E39: 4053.21 | F39: 4267.59 | G39: 2513.02 | H39: =(G39/5)*12 -> 6031.248 | I39: 4500 | J39: =I39*1.03 -> 4635 | K39: =J39*1.03 -> 4774.05 | L39: =K39*1.03 -> 4917.2715 | M39: =L39*1.03 -> 5064.7896
C40: Taxes paid | D40: 321 | E40: 46984 | F40: 12041 | G40: 6 | H40: =(G40/5)*12 -> 14.4 | I40: 12050 | J40: =I40*1.03 -> 12411.5 | K40: =J40*1.03 -> 12783.845 | L40: =K40*1.03 -> 13167.36 | M40: =L40*1.03 -> 13562.381
C41: Property taxes | J41: =I41*1.03 -> 0 | K41: =J41*1.03 -> 0 | L41: =K41*1.03 -> 0 | M41: =L41*1.03 -> 0
C42: Personal Property Taxes | J42: =I42*1.03 -> 0 | K42: =J42*1.03 -> 0 | L42: =K42*1.03 -> 0 | M42: =L42*1.03 -> 0
C43: Travel/Vehicle | D43: 10345.08 | E43: 7316.22 | F43: 6146.39 | G43: 4607.67 | H43: =(G43/5)*12 -> 11058.408 | I43: 150 | J43: =I43*1.03 -> 154.5 | K43: =J43*1.03 -> 159.135 | L43: =K43*1.03 -> 163.90905 | M43: =L43*1.03 -> 168.82632
C44: Utilities | D44: 51978.73 | E44: 59720.53 | F44: 54226.63 | G44: 18662.18 | H44: =(G44/5)*12 -> 44789.232 | I44: 55000 | J44: =I44*1.03 -> 56650 | K44: =J44*1.03 -> 58349.5 | L44: =K44*1.03 -> 60099.985 | M44: =L44*1.03 -> 61902.985
C45: Misc Expense | D45: 33940.91 | E45: 38531.66 | F45: 1664.42 | I45: 1500 | J45: =I45*1.03 -> 1545 | K45: =J45*1.03 -> 1591.35 | L45: =K45*1.03 -> 1639.0905 | M45: =L45*1.03 -> 1688.2632
C46: Total Expenses | D46: =SUM(D15:D45) -> 780961.77 | E46: =SUM(E15:E45) -> 894419.63 | F46: =SUM(F15:F45) -> 826252.97 | G46: =SUM(G15:G45) -> 369315.42 | H46: =SUM(H15:H45) -> 886357.01 | I46: =SUM(I15:I45) -> 804185 | J46: =SUM(J15:J45) -> 828310.55 | K46: =SUM(K15:K45) -> 853159.87 | ... M46: =SUM(M15:M45) -> 905117.3 | N46: =I46 -> 804185
C47: Net Operating Income | D47: =D12-D46 -> 411340.05 | E47: =E12-E46 -> 467961.21 | F47: =F12-F46 -> 593744.96 | G47: =G12-G46 -> 221740.6 | H47: =H12-H46 -> 532177.44 | I47: =I12-I46 -> 658412.87 | J47: =J12-J46 -> 678165.25 | K47: =K12-K46 -> 698510.21 | ... N47: =N12-N46 -> 611227 | O47: 679263
C49: Cap Rate | D49: =D47/'Deal Overview'!$C$5 -> 0.063283085 | E49: =E47/'Deal Overview'!$C$5 -> 0.071994032 | F49: =F47/'Deal Overview'!$C$5 -> 0.091345378 | G49: =G47/'Deal Overview'!$C$5 -> 0.034113938 | H49: =H47/'Deal Overview'!$C$5 -> 0.081873452 | I49: =I47/'Deal Overview'!$C$5 -> 0.10129429 | J49: =J47/'Deal Overview'!$C$5 -> 0.10433312 | K49: =K47/'Deal Overview'!$C$5 -> 0.10746311 | ... M49: =M47/'Deal Overview'!$C$5 -> 0.11400761 | N49: =N47/'Sources and Uses'!$D$5 -> 0.094034923
C50: Expense Ratio | D50: =D46/D12 -> 0.65500342 | E50: =E46/E12 -> 0.65651219 | F50: =F46/F12 -> 0.58186914 | G50: =G46/G12 -> 0.62483996 | H50: =H46/H12 -> 0.62483996 | I50: =I46/I12 -> 0.54983329 | J50: =J46/J12 -> 0.54983329 | K50: =K46/K12 -> 0.54983329 | ... M50: =M46/M12 -> 0.54983329 | N50: =I46/(N13*12) -> 0.56816319
C51: Misc Unforseen/Reserves | I51: 20000 | J51: =I51 -> 20000 | K51: =J51 -> 20000 | L51: =K51 -> 20000 | M51: =L51 -> 20000 | N51: 20000
C52: Mortgage | I52: ='Sources and Uses'!J9 -> 370370.81 | J52: =I52 -> 370370.81 | K52: =J52 -> 370370.81 | L52: =K52 -> 370370.81 | M52: =L52 -> 370370.81 | N52: =I52 -> 370370.81
C53: Asset Management Fees | I53: =I12*0.01 -> 14625.979 | J53: =J12*0.01 -> 15064.758 | K53: =K12*0.01 -> 15516.701 | L53: =L12*0.01 -> 15982.202 | M53: =M12*0.01 -> 16461.668 | N53: =N12*0.01 -> 14154.12
C54: Management Fees | H54: 0.02 | I54: =I12*$H$54 -> 29251.957 | J54: =J12*$H$54 -> 30129.516 | K54: =K12*$H$54 -> 31033.402 | L54: =L12*$H$54 -> 31964.404 | M54: =M12*$H$54 -> 32923.336 | N54: =N12*$H$54 -> 28308.24
C55: Net Cash Fow | I55: =I47-I51-I52-I53-I54 -> 224164.12 | J55: =J47-J51-J52-J53-J54 -> 242600.17 | K55: =K47-K51-K52-K53-K54 -> 261589.3 | L55: =L47-L51-L52-L53-L54 -> 281148.11 | M55: =M47-M51-M52-M53-M54 -> 301293.67 | N55: =N47-N51-N52-N53-N54 -> 178393.83
C56: Return | D56: =D55/'Deal Overview'!$C$8 -> 0 | E56: =E55/'Deal Overview'!$C$8 -> 0 | F56: =F55/'Deal Overview'!$C$8 -> 0 | G56: =G55/'Deal Overview'!$C$8 -> 0 | H56: =H55/'Deal Overview'!$C$8 -> 0 | I56: =I55/'Deal Overview'!$C$8 -> 0.088201505 | J56: =J55/'Deal Overview'!$C$8 -> 0.095455508 | K56: =K55/'Deal Overview'!$C$8 -> 0.10292713 | ... M56: =M55/'Deal Overview'!$C$8 -> 0.11854955 | N56: =N55/'Sources and Uses'!$G$20 -> 0.07019234
C57: Principal Reduction | I57: ='Sources and Uses'!L8 -> Total Principal Reduction | J57: ='Sources and Uses'!M8 -> -74557.694 | K57: ='Sources and Uses'!N8 -> -79590.531 | L57: ='Sources and Uses'!O8 -> -84963.098 | M57: ='Sources and Uses'!P8 -> -90698.327 | N57: ='Sources and Uses'!Q8 -> -96820.698
C58: Loan Balance | I58: ='Sources and Uses'!M9 -> 4475442.3 | J58: ='Sources and Uses'!N9 -> 4395851.8 | K58: ='Sources and Uses'!O9 -> 4310888.7 | L58: ='Sources and Uses'!P9 -> 4220190.3 | M58: ='Sources and Uses'!Q9 -> 4123369.7 | N58: ='Sources and Uses'!R9
C59: Sale Price | I59: =I47/0.08 -> 8230160.8 | J59: =J47/0.08 -> 8477065.7 | K59: =K47/0.08 -> 8731377.6 | L59: =L47/0.08 -> 8993319 | M59: =M47/0.08 -> 9263118.5 | N59: =N47/0.08 -> 7640337.5
C60: Sale Costs | I60: =I59*0.06 -> 493809.65 | J60: =J59*0.06 -> 508623.94 | K60: =K59*0.06 -> 523882.66 | L60: =L59*0.06 -> 539599.14 | M60: =M59*0.06 -> 555787.11 | N60: =N59*0.06 -> 458420.25
C61: Net Proceeds | I61: =I59-I60-I58 -> 3260908.9 | J61: =J59-J60-J58 -> 3572590 | K61: =K59-K60-K58 -> 3896606.3 | L61: =L59-L60-L58 -> 4233529.5 | M61: =M59-M60-M58 -> 4583961.8 | N61: =N59-N60-N58 -> 7181917.2
C62: Investor Preferred Return | D62: 0.08 | I62: ='Sources and Uses'!$D$13*$D$62 -> 203320 | J62: ='Sources and Uses'!$D$13*$D$62 -> 203320 | K62: ='Sources and Uses'!$D$13*$D$62 -> 203320 | L62: ='Sources and Uses'!$D$13*$D$62 -> 203320 | M62: ='Sources and Uses'!$D$13*$D$62 -> 203320 | N62: ='Sources and Uses'!$D$13*$D$62 -> 203320
C63: Sponsor Split | D63: 0.5 | I63: =if((I55-I62)>0,(I55-I62)/2,0) -> 10422.062 | J63: =if((J55-J62)>0,(J55-J62)/2,0) -> 19640.086 | K63: =if((K55-K62)>0,(K55-K62)/2,0) -> 29134.651 | L63: =if((L55-L62)>0,(L55-L62)/2,0) -> 38914.053 | M63: =if((M55-M62)>0,(M55-M62)/2,0) -> 48986.836 | N63: =if((N55-N62)>0,(N55-N62)/2,0) -> 0
C64: Net Estimated Annual Cash Flow to Investors | I64: =I55-I63 -> 213742.06 | J64: =J55-J63 -> 222960.09 | K64: =K55-K63 -> 232454.65 | L64: =L55-L63 -> 242234.05 | M64: =M55-M63 -> 252306.84 | N64: =N55-N63 -> 178393.83
C65: Estimated Return to Investors | I65: =I64/'Sources and Uses'!$D$13 -> 0.084100752 | J65: =J64/'Sources and Uses'!$D$13 -> 0.087727754 | K65: =K64/'Sources and Uses'!$D$13 -> 0.091463565 | L65: =L64/'Sources and Uses'!$D$13 -> 0.095311451 | M65: =M64/'Sources and Uses'!$D$13 -> 0.099274773 | N65: =N64/'Sources and Uses'!$D$13 -> 0.07019234
C67: Total Sponsor Fees
C68: Cash flow Promote | I68: =I63 -> 10422.062 | J68: =J63 -> 19640.086 | K68: =K63 -> 29134.651 | L68: =L63 -> 38914.053 | M68: =M63 -> 48986.836
C69: Disposition Fees if we sell | M69: =M59*0.03 -> 277893.56
C70: Loan Fees | I70: ='Sources and Uses'!D18 -> 45500
C71: Asset Management Fees | I71: =I53 -> 14625.979 | J71: =J53 -> 15064.758 | K71: =K53 -> 15516.701 | L71: =L53 -> 15982.202 | M71: =M53 -> 16461.668
C72: Promote on Sale | M72: =(M61-'Sources and Uses'!D13)*D63 -> 1021230.9
C73: Total Fees | D73: =sum(I68:M72) -> 1569373.4
L76: Equity | M76: ='Sources and Uses'!D13 -> 2541500
I77: 0.0813 | L77: Purchase Price | M77: ='Sources and Uses'!D5 -> 6500000
L78: Sale Price | M78: =M47/0.08 -> 9263118.5
L79: Sale Cost | M79: =M78*0.06 -> 555787.11
L80: Mortgage | M80: ='Sources and Uses'!Q9 -> 4123369.7
L81: Returned to Inv. | M81: =M78-M79-M80 -> 4583961.8
L82: Total Return | M82: =(M81-M76)/M76 -> 0.80364422
L83: Annualized Return | M83: =M82/5 -> 0.16072884
O86: Total Cash Flow | P86: =sum(I55:M55) -> 1310795.4
O87: Total Profit at Sale | P87: =M61-'Sources and Uses'!D13 -> 2042461.8
D88: =D46+D89 -> 858719.26 | E88: =E46+E89 -> 989610.36 | F88: =F46+F89 -> 1045609.6 | G88: =G46+G89 -> 426366.47 | O88: Total | P88: =P87+P86 -> 3353257.2
C89: Expenses Removed | D89: =SUM(D90:D1048604) -> 77757.49 | E89: =SUM(E90:#REF!) -> 95190.73 | F89: =SUM(F90:#REF!) -> 219356.59 | G89: =SUM(G90:#REF!) -> 57051.05 | O89: Total Investor Pref | P89: =sum(I62:M62) -> 1016600
C90: Related Party Rent | D90: 76200 | E90: 94500 | F90: 216146.09 | G90: 55000 | O90: Net to Split | P90: =P88-P89 -> 2336657.2
C91: Owner Meals | D91: 302.63 | E91: 267.59 | F91: 924.19 | G91: 26.68 | O91: Sponsor | P91: =P90/2 -> 1168328.6
C92: Owner Travel | D92: 844.33 | E92: $ - | F92: 1269.69 | O92: Investor Total | P92: =P91+P89 -> 2184928.6
C93: Vehicle Expense | D93: 410.53 | E93: 423.14 | F93: 310 | P93: =P92/'Sources and Uses'!D13 -> 0.8597004
C94: Interest Expense | D94: $ - | E94: $ - | F94: 693.1 | G94: 1471.87
C95: Other Income | D95: $ - | E95: $ - | F95: 13.52
C96: West Jordan | G96: 552.5 | P96: Year 0 | Q96: Year 1 | R96: Year 2 | S96: Year 3 | T96: Year 4 | U96: Year 5
O97: Cash Flow | P97: =-'Sources and Uses'!D13 -> -2541500 | Q97: =I55 -> 224164.12 | R97: =J55 -> 242600.17 | S97: =K55 -> 261589.3 | T97: =L55 -> 281148.11 | U97: =M55 -> 301293.67
O98: Principal Reduction
O99: Net Proceeds from Sale | U99: =M61 -> 4583961.8
O100: Sponsor Share | Q100: =(I55-I62)/2 -> 10422.062 | R100: =(J55-J62)/2 -> 19640.086 | S100: =(K55-K62)/2 -> 29134.651 | T100: =(L55-L62)/2 -> 38914.053 | U100: =((M55-M62)/2)+((U99-'Sources and Uses'!D13)/2) -> 1070217.7
O101: Total to Investor | P101: =P99+P98+P97 -> -2541500 | Q101: =Q99+Q98+Q97-Q100 -> 213742.06 | R101: =R99+R98+R97-R100 -> 222960.09 | S101: =S99+S98+S97-S100 -> 232454.65 | T101: =T99+T98+T97-T100 -> 242234.05 | U101: =U99+U98+U97-U100 -> 3815037.7
O102: Irr | P102: =irr(P101:U101) -> 0.15010871
O103: Total Return | P103: =sum(P101:U101)/'Sources and Uses'!D13 -> 0.8597004
P106: Year 0 | Q106: Year 1 | R106: Year 2 | S106: Year 3 | T106: Year 4 | U106: Year 5
O107: Cash Flow | P107: =P97 -> -2541500 | Q107: =Q97 -> 224164.12 | R107: =R97 -> 242600.17 | S107: =K65 -> 0.091463565 | T107: =L65 -> 0.095311451 | U107: =M65 -> 0.099274773
O108: Principal Reduction
O109: Net Proceeds from Sale | R109: =J61 -> 3572590 | U109: =M91
O110: Sponsor Share | Q110: =Q100 -> 10422.062 | R110: =R100 -> 19640.086 | S110: =(K65-K92)/2 -> 0.045731783 | T110: =(L65-L92)/2 -> 0.047655725 | U110: =((M65-M92)/2)+((U109-'Sources and Uses'!D23)/2) -> -230749.95
...

Sheet 3 Year Proforma
C2: 3 Year Proforma | J2: Actuals
D4: Year 1 | E4: Year 2 | F4: Year 3 | G4: Year 4 | H4: Year 5 | K4: =Proforma!D4 -> 2022 | L4: =Proforma!E4 -> 2023 | M4: =Proforma!F4 -> 2024 | N4: =Proforma!G4 -> 2025 YTD (May) | O4: =Proforma!H4 -> 2025 Annualized
C5: Gross Potential Rent | D5: =166554.6*12 -> 1998655.2 | E5: =D5*1.03 -> 2058614.9 | F5: =E5*1.03 -> 2120373.3
C6: Vacancy @ 5% | D6: =D5*-0.086 -> -171884.35 | E6: =E5*-0.086 -> -177040.88 | F6: =F5*-0.086 -> -182352.1
C7: Other Income | D7: =2842.28*12 -> 34107.36 | E7: =2842.28*12 -> 34107.36 | F7: =2842.28*12 -> 34107.36
C8: Effective Gross Income | D8: =Proforma!I12 -> 1462597.9 | E8: =Proforma!J12 -> 1506475.8 | F8: =Proforma!K12 -> 1551670.1 | G8: =Proforma!L12 -> 1598220.2 | H8: =Proforma!M12 -> 1646166.8 | J8: =C8 -> Effective Gross Income | K8: =Proforma!D12 -> 1192301.8 | L8: =Proforma!E12 -> 1362380.8 | M8: =Proforma!F12 -> 1419997.9 | N8: =Proforma!G12 -> 591056.02 | O8: =Proforma!H12 -> 1418534.4
C9: Expenses | D9: =Proforma!I46 -> 804185 | E9: =Proforma!J46 -> 828310.55 | F9: =Proforma!K46 -> 853159.87 | G9: =Proforma!L46 -> 878754.66 | H9: =Proforma!M46 -> 905117.3 | J9: =C9 -> Expenses | K9: =Proforma!D46 -> 780961.77 | L9: =Proforma!E46 -> 894419.63 | M9: =Proforma!F46 -> 826252.97 | N9: =Proforma!G46 -> 369315.42 | O9: =Proforma!H46 -> 886357.01
C11: Net Operating Income | D11: =D8-D9 -> 658412.87 | E11: =E8-E9 -> 678165.25 | F11: =F8-F9 -> 698510.21 | G11: =G8-G9 -> 719465.52 | H11: =H8-H9 -> 741049.48 | J11: =C11 -> Net Operating Income | K11: =K8-K9 -> 411340.05 | L11: =L8-L9 -> 467961.21 | M11: =M8-M9 -> 593744.96 | N11: =N8-N9 -> 221740.6 | O11: =O8-O9 -> 532177.44
J13: Excluded Expenses
J14: Owner HSA
J15: Owner Life Insurance
J16: Owner Salary
J17: Owner Vehicle
J18: Owner Storage Unit
J19: Owner Short Term Interst
J20: Owner Other Income
J21: Owner Mortgage Payment
H26: =H10+H18 -> 0 | I26: =I10+I18 -> 0 | J26: =J10+J18 -> #VALUE!

Sheet Reimbursements
D1: Check | E1: Deposited to
A2: Earnest Money | B2: Cory 1031 Money
A3: Apprisal
A4: Inspection
A5: Environmental

Sheet Capital Stack
A1: Investor | B1: Amount | C1: Name/Entity | D1: Final Ownership | E1: Ownership | F1: Email | G1: Identifier | H1: Signed Docs | I1: Wire | J1: Both
D2: =E2*0.1 -> #DIV/0! | E2: =B2/$B$15 -> #DIV/0!
D3: =E3*0.1 -> #DIV/0! | E3: =B3/$B$15 -> #DIV/0!
D4: =E4*0.1 -> #DIV/0! | E4: =B4/$B$15 -> #DIV/0!
D5: =E5*0.1 -> #DIV/0! | E5: =B5/$B$15 -> #DIV/0!
D6: =E6*0.1 -> #DIV/0! | E6: =B6/$B$15 -> #DIV/0!
D7: =E7*0.1 -> #DIV/0! | E7: =B7/$B$15 -> #DIV/0!
D8: =E8*0.1 -> #DIV/0! | E8: =B8/$B$15 -> #DIV/0!
D9: =E9*0.1 -> #DIV/0! | E9: =B9/$B$15 -> #DIV/0!
D10: =E10*0.1 -> #DIV/0! | E10: =B10/$B$15 -> #DIV/0!
D11: =E11*0.1 -> #DIV/0! | E11: =B11/$B$15 -> #DIV/0!
D12: =E12*0.1 -> #DIV/0! | E12: =B12/$B$15 -> #DIV/0!
D13: 0.45
D14: 0.45
A15: Total | B15: =SUM(B2:B14) -> 0
A16: Remaining
A19: Reached out | C19: Followed up.
A20: Cam Cope | B20: Maybe | C20: 45222
A23: Bryan Griffiths | B23: Maybe | C23: 45222
A24: Alex Smith | B24: Maybe
A25: Randy Clayton
A27: Ben Clayton
A28: Jeff Meihoffer
A29: Rich Toloti | B29: Maybe
A30: Woody Klemetson
A31: Sterling Snow
A32: Blakely Cragun
A33: Adam and Andrew Law
A34: Ray Dodd
A35: Todd Orullian
A36: Adam Christensen
A37: Matt Boardman
A38: Scott Eliason
A39: Devin Deaton | B39: No
A40: Cameron Lee | B40: No
A41: Eric Motzkus | B41: No
A42: Aaron Meier | B42: No
A43: Mike Peterson | B43: No
A44: Jon Waddoups | B44: No
A45: Joel Reichert | B45: No
A46: Brad and Emily Forsyth | B46: No
A47: James Brewster | B47: No
A48: Lance Jorgenson | B48: No
A49: Dave Soper | B49: No
A51: Potential Others
A55: American Enterprises
A56: Jake Despain
